[ {
  "location" : "-",
  "county" : "-",
  "state" : "Indiana",
  "directions" : "Northernmost Indiana in marl pits in Pleistocene lake bed deposits",
  "age" : "Pleistocene",
  "formation" : "",
  "fossils" : "small gastropods,bivalves,ostracods",
  "comments" : "",
  "reference" : "",
  "latLong" : ""
}, {
  "location" : "-",
  "county" : "-",
  "state" : "Indiana",
  "directions" : "Ohio River Valley in occasional exposures of yellow silt",
  "age" : "Pleistocene",
  "formation" : "",
  "fossils" : "small gastropods,bivalves,ostracods",
  "comments" : "",
  "reference" : "",
  "latLong" : ""
}, {
  "location" : "-",
  "county" : "-",
  "state" : "Indiana",
  "directions" : "Wabash River Valley in occasional exposures of yellow silt",
  "age" : "Pleistocene",
  "formation" : "",
  "fossils" : "small gastropods,bivalves,ostracods",
  "comments" : "",
  "reference" : "",
  "latLong" : ""
}, {
  "location" : "-",
  "county" : "-",
  "state" : "Indiana",
  "directions" : "on IN56 In outcrop with geodes",
  "age" : "Mississippian",
  "formation" : "",
  "fossils" : "brachiopods,conularids,shark teeth,pectens,crinoid columns",
  "comments" : "IN0246",
  "reference" : "",
  "latLong" : ""
}, {
  "location" : "Jay City",
  "county" : "Adams",
  "state" : "Indiana",
  "directions" : "area quarries",
  "age" : "Silurian",
  "formation" : "Huntington",
  "fossils" : "Favosites,Halysites,Heliolites,Zaphrentis,Atrypa,Leptaena,Meristina,Pentamerus,Stropheodonta,Orthoceras",
  "comments" : "IN0002",
  "reference" : "",
  "latLong" : ""
}, {
  "location" : "-",
  "county" : "Allen",
  "state" : "Indiana",
  "directions" : "in thin shale band",
  "age" : "Devonian",
  "formation" : "Silica",
  "fossils" : "Phacops",
  "comments" : "IN0007",
  "reference" : "",
  "latLong" : ""
}, {
  "location" : "Woodburn",
  "county" : "Allen",
  "state" : "Indiana",
  "directions" : "between Hwy 24 and Maumee River",
  "age" : "Devonian Middle",
  "formation" : "Silica|Tenmile Creek",
  "fossils" : "cnidarians,crinoids,bryozoa,placoderms,trilobites,brachiopods,ostracods,trace fossils",
  "comments" : "IN0003",
  "reference" : "",
  "latLong" : ""
}, {
  "location" : "Woodburn",
  "county" : "Allen",
  "state" : "Indiana",
  "directions" : "between IN24 and Maumee River in quarry",
  "age" : "Devonian",
  "formation" : "Dundee",
  "fossils" : "Cnidarians,crinoids,bryozoa,placoderms,trace fossils,brachiopods,trilobites,ostracods",
  "comments" : "IN0004",
  "reference" : "",
  "latLong" : ""
}, {
  "location" : "Woodburn",
  "county" : "Allen",
  "state" : "Indiana",
  "directions" : "between Maumee River and IN24 in quarry",
  "age" : "Devonian",
  "formation" : "Dundee Limestone",
  "fossils" : "coral,crinoids,bryozoa,brachiopods,trilobites,trace fossils.",
  "comments" : "IN0005",
  "reference" : "",
  "latLong" : ""
}, {
  "location" : "Woodburn",
  "county" : "Allen",
  "state" : "Indiana",
  "directions" : "in quarry between Maumee R and IN24",
  "age" : "Devonian",
  "formation" : "Dundee|Silica|Tenmile Creek",
  "fossils" : "broad fauna",
  "comments" : "IN0006",
  "reference" : "",
  "latLong" : ""
}, {
  "location" : "Elizabethtown",
  "county" : "Bartholomew",
  "state" : "Indiana",
  "directions" : "3.5 km NE at Meshberger Stone Co quarry",
  "age" : "Devonian",
  "formation" : "",
  "fossils" : "abundant stromatoporoids,brachiopods,corals",
  "comments" : "IN0008",
  "reference" : "",
  "latLong" : ""
}, {
  "location" : "Hartsville",
  "county" : "Bartholomew",
  "state" : "Indiana",
  "directions" : "",
  "age" : "Silurian",
  "formation" : "",
  "fossils" : "brachiopods,blastoids,corals",
  "comments" : "IN0009",
  "reference" : "",
  "latLong" : ""
}, {
  "location" : "Hartsville",
  "county" : "Bartholomew",
  "state" : "Indiana",
  "directions" : "At Anderson Falls on Fall Fork of Clifty Creek",
  "age" : "Silurian",
  "formation" : "Waldron",
  "fossils" : "Trilobites,crinoids",
  "comments" : "IN0010",
  "reference" : "",
  "latLong" : ""
}, {
  "location" : "Hartsville",
  "county" : "Bartholomew",
  "state" : "Indiana",
  "directions" : "In quarry on IN46 at edge of town and in adjacent creek banks and road cuts",
  "age" : "Silurian",
  "formation" : "Waldron",
  "fossils" : "Good collecting",
  "comments" : "IN0011",
  "reference" : "",
  "latLong" : ""
}, {
  "location" : "Hartsville",
  "county" : "Bartholomew",
  "state" : "Indiana",
  "directions" : "SW of town in quarry on NW side of IN46 in roadcuts on SE side of the highway in blue-gray shale between two limestones. NE1/4S2T9NR7E",
  "age" : "Silurian",
  "formation" : "",
  "fossils" : "-",
  "comments" : "",
  "reference" : "",
  "latLong" : "https://scholarworks.iu.edu/ dspace/bitstream/2022/280/1/C06.pdf"
}, {
  "location" : "Delphi",
  "county" : "Carroll",
  "state" : "Indiana",
  "directions" : "Area exposures in Wabash Valley between Delphi and Huntington",
  "age" : "Silurian",
  "formation" : "",
  "fossils" : "Poorly preserved reef fossils",
  "comments" : "",
  "reference" : "",
  "latLong" : "https://scholarworks.iu.edu/ dspace/bitstream/2022/280/1/C06.pdf"
}, {
  "location" : "Delphi",
  "county" : "Carroll",
  "state" : "Indiana",
  "directions" : "In Delphi Limestone Co Quarry at NW edge of town on N side US421.",
  "age" : "Devonian Middle",
  "formation" : "New Albany Shale",
  "fossils" : "Conularids - Ctenoconularia.",
  "comments" : "IN0012",
  "reference" : "",
  "latLong" : ""
}, {
  "location" : "Delphi",
  "county" : "Carroll",
  "state" : "Indiana",
  "directions" : "In the Stuntz-Yeoman Quarry to NW",
  "age" : "Silurian",
  "formation" : "",
  "fossils" : "Poorly preserved,but abundant brachiopods",
  "comments" : "IN0013",
  "reference" : "",
  "latLong" : ""
}, {
  "location" : "Delphi",
  "county" : "Carroll",
  "state" : "Indiana",
  "directions" : "NW at Stuntz-Yeoman quarry",
  "age" : "Silurian",
  "formation" : "",
  "fossils" : "brachiopods",
  "comments" : "IN0014",
  "reference" : "",
  "latLong" : ""
}, {
  "location" : "Delphi",
  "county" : "Carroll",
  "state" : "Indiana",
  "directions" : "W in Stunz-Yeoman Co Quarry 1.3km NW of IN25 IN39 Junction",
  "age" : "Silurian",
  "formation" : "",
  "fossils" : "Poorly preserved reef fossils",
  "comments" : "",
  "reference" : "",
  "latLong" : "https://scholarworks.iu.edu/ dspace/bitstream/2022/280/1/C06.pdf"
}, {
  "location" : "Delphi",
  "county" : "Carroll",
  "state" : "Indiana",
  "directions" : "in quarry on N side US21",
  "age" : "",
  "formation" : "",
  "fossils" : "conularids",
  "comments" : "IN0015",
  "reference" : "",
  "latLong" : ""
}, {
  "location" : "Georgetown",
  "county" : "Cass",
  "state" : "Indiana",
  "directions" : "2 km E at Cedar Rapids on Wabash River in marble like pinkish Limestone and S for 2 km",
  "age" : "Silurian",
  "formation" : "",
  "fossils" : "many brachiopods -- Conchidium,Wilsonia[?],others ; corals;stromatoporoids",
  "comments" : "IN0016",
  "reference" : "'Wilsonia' is a bird - a warbler. Probably 'Wilsoniella' a Paleozoic brachiopod",
  "latLong" : ""
}, {
  "location" : "Georgetown",
  "county" : "Cass",
  "state" : "Indiana",
  "directions" : "area gullies",
  "age" : "",
  "formation" : "",
  "fossils" : "silicified shells.",
  "comments" : "IN0019",
  "reference" : "There is no Georgetown County in Indiana. There are six(!) towns named 'Georgetown' in the state. I'd go with the one in Cass county which is the only Georgetown near a large body of water -- the Wabash River.",
  "latLong" : ""
}, {
  "location" : "Logansport",
  "county" : "Cass",
  "state" : "Indiana",
  "directions" : "3.6km E in France Stone Co Quarry NE1/4S27T27NR2E",
  "age" : "Silurian-Devonian",
  "formation" : "",
  "fossils" : "Corals",
  "comments" : "",
  "reference" : "",
  "latLong" : "https://scholarworks.iu.edu/ dspace/bitstream/2022/280/1/C06.pdf"
}, {
  "location" : "Logansport",
  "county" : "Cass",
  "state" : "Indiana",
  "directions" : "7 km E just N of US24 in quarry",
  "age" : "Devonian",
  "formation" : "",
  "fossils" : "corals,stromatoporoids",
  "comments" : "IN0017",
  "reference" : "",
  "latLong" : ""
}, {
  "location" : "Logansport",
  "county" : "Cass",
  "state" : "Indiana",
  "directions" : "in area quarries",
  "age" : "",
  "formation" : "",
  "fossils" : "marine fossils",
  "comments" : "IN0018",
  "reference" : "",
  "latLong" : ""
}, {
  "location" : "-",
  "county" : "Clark",
  "state" : "Indiana",
  "directions" : "In a bone bed at the top of the Jeffersonville Limestone. Abundant vertebrate fossils at one (unspecified) quarry site",
  "age" : "Devonian",
  "formation" : "Jeffersonville",
  "fossils" : "vertebrates;fish teeth,bones",
  "comments" : "",
  "reference" : "",
  "latLong" : "http://www.lakeneosho.org/Temp91.html"
}, {
  "location" : "-",
  "county" : "Clark",
  "state" : "Indiana",
  "directions" : "in chert beds",
  "age" : "Devonian",
  "formation" : "New Castle Chert",
  "fossils" : "Phacops",
  "comments" : "IN0041",
  "reference" : "",
  "latLong" : ""
}, {
  "location" : "Borden",
  "county" : "Clark",
  "state" : "Indiana",
  "directions" : "6 km SW in sand pit in chert cobbles",
  "age" : "Paleocene",
  "formation" : "",
  "fossils" : "corals - Lithostrotionella,bryozoa,gastropods,pelecypods,ostracods",
  "comments" : "IN0020",
  "reference" : "",
  "latLong" : ""
}, {
  "location" : "Carwood",
  "county" : "Clark",
  "state" : "Indiana",
  "directions" : "In roadcut 1.6km N in green shale S4T1SR6E",
  "age" : "Mississippian",
  "formation" : "",
  "fossils" : "fossils",
  "comments" : "",
  "reference" : "",
  "latLong" : "https://scholarworks.iu.edu/dspace/bitstream/2022/280/1/C06.pdf"
}, {
  "location" : "Charleston",
  "county" : "Clark",
  "state" : "Indiana",
  "directions" : "3.8 km E in Road Cut on E side of IN62 / Fourteen Mile Creek 43km W of entrance to Clifty Falls State Park in 40m of Ordovician-Silurian beds",
  "age" : "Ordovician-Devonian",
  "formation" : "Richmond|Waldron|Jeffersonville",
  "fossils" : "abundant fossils in some layers",
  "comments" : "IN0021",
  "reference" : "",
  "latLong" : ""
}, {
  "location" : "Charleston",
  "county" : "Clark",
  "state" : "Indiana",
  "directions" : "NE in Charleston Quarry",
  "age" : "Silurian-Devonian",
  "formation" : "Louisville|Jeffersonville",
  "fossils" : "A few fossils",
  "comments" : "IN0022",
  "reference" : "",
  "latLong" : ""
}, {
  "location" : "Charlestown",
  "county" : "Clark",
  "state" : "Indiana",
  "directions" : "",
  "age" : "",
  "formation" : "",
  "fossils" : "Bryozoa Syringopora",
  "comments" : "IN0023",
  "reference" : "",
  "latLong" : ""
}, {
  "location" : "Charlestown",
  "county" : "Clark",
  "state" : "Indiana",
  "directions" : "",
  "age" : "",
  "formation" : "",
  "fossils" : "pelecypod Paracyclas",
  "comments" : "IN0024",
  "reference" : "",
  "latLong" : ""
}, {
  "location" : "Charlestown-Speed-Sellersburg area",
  "county" : "Clark",
  "state" : "Indiana",
  "directions" : "",
  "age" : "",
  "formation" : "",
  "fossils" : "Brachiopods - Desquamatia",
  "comments" : "IN0025",
  "reference" : "",
  "latLong" : ""
}, {
  "location" : "Clarksville",
  "county" : "Clark",
  "state" : "Indiana",
  "directions" : "At Falls Of the Ohio State Park. Exit 0 on I65 and follow signs West to park",
  "age" : "Silurian",
  "formation" : "Waldron",
  "fossils" : "Dump material from quarries sometimes available at the park for collecting",
  "comments" : "IN0026",
  "reference" : "",
  "latLong" : ""
}, {
  "location" : "Claysburg",
  "county" : "Clark",
  "state" : "Indiana",
  "directions" : "2 km N in quarry",
  "age" : "Devonian",
  "formation" : "",
  "fossils" : "brachiopods",
  "comments" : "IN0027",
  "reference" : "",
  "latLong" : ""
}, {
  "location" : "Corn Island",
  "county" : "Clark",
  "state" : "Indiana",
  "directions" : "Opposite Louisville,KY--Largely removed by quarrying and subsequently flooded by downstream navigation lock",
  "age" : "Devonian",
  "formation" : "New Albany",
  "fossils" : "fish-Dinichthys",
  "comments" : "IN0028",
  "reference" : "",
  "latLong" : ""
}, {
  "location" : "Falls of the Ohio",
  "county" : "Clark",
  "state" : "Indiana",
  "directions" : "",
  "age" : "Devonian",
  "formation" : "Onondaga Limestones",
  "fossils" : "Corals,Pleurodictyum",
  "comments" : "IN0029",
  "reference" : "",
  "latLong" : ""
}, {
  "location" : "Falls of the Ohio",
  "county" : "Clark",
  "state" : "Indiana",
  "directions" : "2 km downstream from bridge",
  "age" : "",
  "formation" : "",
  "fossils" : "shells",
  "comments" : "IN0030",
  "reference" : "",
  "latLong" : ""
}, {
  "location" : "Falls of the Ohio",
  "county" : "Clark",
  "state" : "Indiana",
  "directions" : "at Indiana side of falls",
  "age" : "",
  "formation" : "",
  "fossils" : "corals and shells 2 meters above",
  "comments" : "IN0031",
  "reference" : "",
  "latLong" : ""
}, {
  "location" : "Jeffersonville",
  "county" : "Clark",
  "state" : "Indiana",
  "directions" : "W on Riverside Drive near Pennsylvannia RR Bridge and Dam 41 in river bank",
  "age" : "Devonian",
  "formation" : "",
  "fossils" : "fossils",
  "comments" : "",
  "reference" : "",
  "latLong" : "https://scholarworks.iu.edu/dspace/bitstream/2022/280/1/C06.pdf"
}, {
  "location" : "Jeffersonville",
  "county" : "Clark",
  "state" : "Indiana",
  "directions" : "in quarry (permission reqd)in clay fills",
  "age" : "Devonian",
  "formation" : "North Vernon",
  "fossils" : "diverse silicified fossils",
  "comments" : "IN0032",
  "reference" : "",
  "latLong" : ""
}, {
  "location" : "Jeffersonville",
  "county" : "Clark",
  "state" : "Indiana",
  "directions" : "in quarry (permission reqd)in spoil piles",
  "age" : "Silurian",
  "formation" : "Waldron",
  "fossils" : "diverse fossils",
  "comments" : "IN0033",
  "reference" : "",
  "latLong" : ""
}, {
  "location" : "Sellersburg",
  "county" : "Clark",
  "state" : "Indiana",
  "directions" : "",
  "age" : "Devonian",
  "formation" : "",
  "fossils" : "corals",
  "comments" : "IN0034",
  "reference" : "",
  "latLong" : ""
}, {
  "location" : "Sellersburg",
  "county" : "Clark",
  "state" : "Indiana",
  "directions" : "Sellersburg Quarry in exposure of Upper Silurian and Devonian formations",
  "age" : "Silurian-Devonian",
  "formation" : "",
  "fossils" : "fossils",
  "comments" : "IN0035",
  "reference" : "",
  "latLong" : ""
}, {
  "location" : "Speed",
  "county" : "Clark",
  "state" : "Indiana",
  "directions" : "In Essroc Quarry-Edgewood fauna",
  "age" : "Devonian Middle",
  "formation" : "",
  "fossils" : "Abundant diverse fossils",
  "comments" : "IN0247",
  "reference" : "",
  "latLong" : ""
}, {
  "location" : "Speed",
  "county" : "Clark",
  "state" : "Indiana",
  "directions" : "Louisville Cement Company Quarry in good exposure of Upper Silurian and Devonian formations",
  "age" : "Silurian-Devonian",
  "formation" : "",
  "fossils" : "fossils",
  "comments" : "IN0037",
  "reference" : "",
  "latLong" : ""
}, {
  "location" : "Speed",
  "county" : "Clark",
  "state" : "Indiana",
  "directions" : "at Louisville Cement Co Quarry",
  "age" : "Devonian",
  "formation" : "",
  "fossils" : "Corals and brachiopods",
  "comments" : "IN0038",
  "reference" : "",
  "latLong" : ""
}, {
  "location" : "Speed",
  "county" : "Clark",
  "state" : "Indiana",
  "directions" : "in quarry in 2 meter thick Limestone",
  "age" : "Devonian",
  "formation" : "Speed Limestone",
  "fossils" : "bryozoa,brachiopods,corals",
  "comments" : "IN0039",
  "reference" : "",
  "latLong" : ""
}, {
  "location" : "Utica",
  "county" : "Clark",
  "state" : "Indiana",
  "directions" : "",
  "age" : "",
  "formation" : "",
  "fossils" : "Coral Stromatopora",
  "comments" : "IN0040",
  "reference" : "",
  "latLong" : ""
}, {
  "location" : "Indian Creek",
  "county" : "Clark?",
  "state" : "Indiana",
  "directions" : "",
  "age" : "Mississippian",
  "formation" : "",
  "fossils" : "Crinoids --Synbathocrinus",
  "comments" : "IN0042",
  "reference" : "",
  "latLong" : ""
}, {
  "location" : "Cloverland",
  "county" : "Clay",
  "state" : "Indiana",
  "directions" : "",
  "age" : "",
  "formation" : "",
  "fossils" : "Cephalopod Temnocheilus",
  "comments" : "IN0043",
  "reference" : "",
  "latLong" : ""
}, {
  "location" : "Coal City",
  "county" : "Clay",
  "state" : "Indiana",
  "directions" : "old coal pits along county line. 1.6km N, W of IN159 in shaly limestone SE1/4S2T9NR6W",
  "age" : "Pennsylvanian",
  "formation" : "",
  "fossils" : "corals, brachiopods,microfossils",
  "comments" : "",
  "reference" : "",
  "latLong" : "https://scholarworks.iu.edu/dspace/bitstream/2022/280/1/C06.pdf"
}, {
  "location" : "Alton",
  "county" : "Crawford",
  "state" : "Indiana",
  "directions" : "5 km NW",
  "age" : "Mississippian",
  "formation" : "Beech Creek Limestone",
  "fossils" : "a few brachiopods,crinoid stems",
  "comments" : "IN0044",
  "reference" : "",
  "latLong" : ""
}, {
  "location" : "Eckerty",
  "county" : "Crawford",
  "state" : "Indiana",
  "directions" : "1 km S of junction of IN145 and IN64 in quarry",
  "age" : "Mississippian",
  "formation" : "Glen Dean",
  "fossils" : "crinoids,brachiopods,blastoids",
  "comments" : "IN0045",
  "reference" : "",
  "latLong" : ""
}, {
  "location" : "Eckerty",
  "county" : "Crawford",
  "state" : "Indiana",
  "directions" : "3.5 km N of junction of IN145 and IN64 near Mulzer Brothers quarry in shale and Limestone on quarry dumps--This appears to be a garbled description of a site 1km S of IN145 IN64 junction",
  "age" : "Mississippian",
  "formation" : "",
  "fossils" : "abundant,well-preserved fossils",
  "comments" : "IN0046",
  "reference" : "",
  "latLong" : ""
}, {
  "location" : "Eckerty",
  "county" : "Crawford",
  "state" : "Indiana",
  "directions" : "4 km N and 1 km S of junction of IN145 and IN64 in quarry",
  "age" : "",
  "formation" : "",
  "fossils" : "fenestrate bryozoa",
  "comments" : "IN0047",
  "reference" : "",
  "latLong" : ""
}, {
  "location" : "Eckerty",
  "county" : "Crawford",
  "state" : "Indiana",
  "directions" : "In Mulzer Brothers quarry 1.3km S of IN145 IN64 junction.",
  "age" : "Mississippian",
  "formation" : "Glen Dean",
  "fossils" : "Crinoids,brachiopods,bryozoa,blastoids",
  "comments" : "IN0048",
  "reference" : "",
  "latLong" : ""
}, {
  "location" : "English",
  "county" : "Crawford",
  "state" : "Indiana",
  "directions" : "5 km N in abandoned quarry",
  "age" : "",
  "formation" : "",
  "fossils" : "crinoid stems,brachiopods,tetracorals",
  "comments" : "IN0049",
  "reference" : "",
  "latLong" : ""
}, {
  "location" : "Grantsburg",
  "county" : "Crawford",
  "state" : "Indiana",
  "directions" : "",
  "age" : "Mississippian",
  "formation" : "",
  "fossils" : "fossils",
  "comments" : "IN0248",
  "reference" : "",
  "latLong" : ""
}, {
  "location" : "Grantsburg",
  "county" : "Crawford",
  "state" : "Indiana",
  "directions" : "several km N on IN37 in road cut",
  "age" : "Mississippian",
  "formation" : "Chester",
  "fossils" : "blastoids,brachiopods,bryozoa,conularia,corals,crinoids,mollusks,shark teeth,trilobites",
  "comments" : "IN0051",
  "reference" : "",
  "latLong" : ""
}, {
  "location" : "Marengo",
  "county" : "Crawford",
  "state" : "Indiana",
  "directions" : "",
  "age" : "Mississippian",
  "formation" : "",
  "fossils" : "fossils",
  "comments" : "IN0249",
  "reference" : "",
  "latLong" : ""
}, {
  "location" : "Milltown",
  "county" : "Crawford",
  "state" : "Indiana",
  "directions" : "In quarries",
  "age" : "",
  "formation" : "",
  "fossils" : "fossils shells.",
  "comments" : "IN0053",
  "reference" : "",
  "latLong" : ""
}, {
  "location" : "Sulfur",
  "county" : "Crawford",
  "state" : "Indiana",
  "directions" : "1 km E in road cuts on IN62 near Little Blue River",
  "age" : "Mississippian",
  "formation" : "",
  "fossils" : "extensive faunas",
  "comments" : "IN0054",
  "reference" : "",
  "latLong" : ""
}, {
  "location" : "Sulfur",
  "county" : "Crawford",
  "state" : "Indiana",
  "directions" : "In road cuts on Hwy 62 on W bluff of Little Blue River 0.8km E.",
  "age" : "Mississippian",
  "formation" : "Glen Dean",
  "fossils" : "Extensive faunas.",
  "comments" : "IN0055",
  "reference" : "",
  "latLong" : ""
}, {
  "location" : "Sulphur",
  "county" : "Crawford",
  "state" : "Indiana",
  "directions" : "2 km se on SW side of IN62",
  "age" : "Mississippian",
  "formation" : "Beech Creek Limestone",
  "fossils" : "brachiopods,large crinoid stems",
  "comments" : "IN0056",
  "reference" : "",
  "latLong" : ""
}, {
  "location" : "Sulphur",
  "county" : "Crawford",
  "state" : "Indiana",
  "directions" : "Intersection of I64 and IN37 (Exit 86) in road cut",
  "age" : "Mississippian",
  "formation" : "Beech Creek Limestone|Tar Springs|Haney|Hardinsburg",
  "fossils" : "blastoids,brachiopods,bryozoa,conularia,corals,crinoids,mollusks,shark teeth,trilobites",
  "comments" : "IN0057",
  "reference" : "",
  "latLong" : ""
}, {
  "location" : "Sulphur",
  "county" : "Crawford",
  "state" : "Indiana",
  "directions" : "at IN37 I64 junction in large road cut",
  "age" : "Mississippian",
  "formation" : "Haney|Indian Springs (IN) Shale",
  "fossils" : "brachiopods,blastoids,crinoids,pelecypods,bryozoa,brachiopods,gastropods,conularids,horn corals,shark teeth and scales,cephalopods,trace fossils,and occasional trilobites.",
  "comments" : "IN0058",
  "reference" : "",
  "latLong" : ""
}, {
  "location" : "Sulphur",
  "county" : "Crawford",
  "state" : "Indiana",
  "directions" : "in road cuts along IN62 along Little Blue River",
  "age" : "Mississippian",
  "formation" : "",
  "fossils" : "invertebrates,classic crinoid site",
  "comments" : "IN0059",
  "reference" : "",
  "latLong" : ""
}, {
  "location" : "Wyandotte Cave",
  "county" : "Crawford",
  "state" : "Indiana",
  "directions" : "A few km W",
  "age" : "Mississippian",
  "formation" : "Chester",
  "fossils" : "vertebrates-Gyracanthus",
  "comments" : "IN0060",
  "reference" : "",
  "latLong" : ""
}, {
  "location" : "Lawrenceburg",
  "county" : "Dearborn",
  "state" : "Indiana",
  "directions" : "W in roadcut On E side of IN48 as it goes up Ohio River bluff W1/2S15T5NR1W",
  "age" : "Ordovician",
  "formation" : "",
  "fossils" : "-",
  "comments" : "",
  "reference" : "",
  "latLong" : "https://scholarworks.iu.edu/ dspace/bitstream/2022/280/1/C06.pdf"
}, {
  "location" : "St Leon",
  "county" : "Dearborn",
  "state" : "Indiana",
  "directions" : "1.6km E in roadcuts on US46",
  "age" : "Ordovician",
  "formation" : "Richmond",
  "fossils" : "Brachiopods-Rafinesquina;Bryozoa",
  "comments" : "IN0061",
  "reference" : "",
  "latLong" : ""
}, {
  "location" : "Weisburg",
  "county" : "Dearborn",
  "state" : "Indiana",
  "directions" : "",
  "age" : "Ordovician",
  "formation" : "",
  "fossils" : "Brachiopods - Sowerbyella",
  "comments" : "IN0062",
  "reference" : "",
  "latLong" : ""
}, {
  "location" : "Weisburg",
  "county" : "Dearborn",
  "state" : "Indiana",
  "directions" : "",
  "age" : "Ordovician Upper",
  "formation" : "Maysville|Waynesville",
  "fossils" : "brachiopods - Platystrophia,Rafinesquina",
  "comments" : "IN0063",
  "reference" : "",
  "latLong" : ""
}, {
  "location" : "Weisburg",
  "county" : "Dearborn",
  "state" : "Indiana",
  "directions" : "In 14.4km of RR cuts between Weisburg and Guilford. Fossils are more abundant near Weisburg but are found throughout the cuts",
  "age" : "Ordovician",
  "formation" : "",
  "fossils" : "-",
  "comments" : "",
  "reference" : "",
  "latLong" : "https://scholarworks.iu.edu/ dspace/bitstream/2022/280/1/C06.pdf"
}, {
  "location" : "Weisburg",
  "county" : "Dearborn",
  "state" : "Indiana",
  "directions" : "In RR Cuts",
  "age" : "Ordovician",
  "formation" : "Richmond",
  "fossils" : "fossils - trilobites",
  "comments" : "IN0064",
  "reference" : "",
  "latLong" : ""
}, {
  "location" : "Weisburg",
  "county" : "Dearborn",
  "state" : "Indiana",
  "directions" : "Railroad cuts near Weisburg,In",
  "age" : "Ordovician",
  "formation" : "Richmond",
  "fossils" : "Waynesville - Elkhorn",
  "comments" : "IN0065",
  "reference" : "",
  "latLong" : ""
}, {
  "location" : "Wilmington",
  "county" : "Dearborn",
  "state" : "Indiana",
  "directions" : "2.1km W in road cut on IN350",
  "age" : "Ordovician",
  "formation" : "Richmond",
  "fossils" : "Brachiopods-Dalmanella;gastropods,bryozoa",
  "comments" : "IN0066",
  "reference" : "",
  "latLong" : ""
}, {
  "location" : "Sandusky",
  "county" : "Decatur",
  "state" : "Indiana",
  "directions" : "500 meters E in Vail Stone Co Quarry",
  "age" : "Silurian",
  "formation" : "",
  "fossils" : "fossils",
  "comments" : "IN0067",
  "reference" : "",
  "latLong" : ""
}, {
  "location" : "Waldron",
  "county" : "Decatur",
  "state" : "Indiana",
  "directions" : "500 meters E in Vail Stone Co Quarry",
  "age" : "Silurian",
  "formation" : "",
  "fossils" : "varied brachiopods",
  "comments" : "IN0068",
  "reference" : "",
  "latLong" : ""
}, {
  "location" : "St Paul",
  "county" : "Decatur?",
  "state" : "Indiana",
  "directions" : "In quarry a few hundred meters NW of town and W of RR tracks.",
  "age" : "Silurian",
  "formation" : "Waldron",
  "fossils" : "?",
  "comments" : "IN0069",
  "reference" : "",
  "latLong" : ""
}, {
  "location" : "Holland",
  "county" : "Dubois",
  "state" : "Indiana",
  "directions" : "2 km SE E of a culvert on Pokeberry creek on IN161",
  "age" : "Pennsylvanian",
  "formation" : "Staunton",
  "fossils" : "Annelids - Sirorbis; crinoid columnals; bryozoa - Prismopora,Rhombopora; brachiopods -Hustedia,Composita,Marginifera; gastropods; ostracods -Amphissites,Bairdia; trilobite fragments,conodonts; forams",
  "comments" : "IN0070",
  "reference" : "",
  "latLong" : ""
}, {
  "location" : "Edwardsville",
  "county" : "Floyd",
  "state" : "Indiana",
  "directions" : "",
  "age" : "Mississippian",
  "formation" : "Keokuk",
  "fossils" : "Fish teeth-Cochliodus",
  "comments" : "IN0071",
  "reference" : "",
  "latLong" : ""
}, {
  "location" : "Edwardsville",
  "county" : "Floyd",
  "state" : "Indiana",
  "directions" : "",
  "age" : "Mississippian",
  "formation" : "Salem",
  "fossils" : "fish teeth-Helodus",
  "comments" : "IN0072",
  "reference" : "",
  "latLong" : ""
}, {
  "location" : "Edwardsville",
  "county" : "Floyd",
  "state" : "Indiana",
  "directions" : "",
  "age" : "Mississippian",
  "formation" : "Warsaw",
  "fossils" : "Shark teeth-Petalodus",
  "comments" : "IN0073",
  "reference" : "",
  "latLong" : ""
}, {
  "location" : "Floyds Knobs",
  "county" : "Floyd",
  "state" : "Indiana",
  "directions" : "Just off I64 at Greenville exit 119",
  "age" : "Mississippian",
  "formation" : "Edwardsville|Ramp Creek",
  "fossils" : "brachiopods,bryozoa,crinoids,ichnofossils",
  "comments" : "IN0074",
  "reference" : "",
  "latLong" : ""
}, {
  "location" : "Attica",
  "county" : "Fountain",
  "state" : "Indiana",
  "directions" : "old shale pit 1.6km NE. S of secondary road and near RR tracks. SE1/4S32T22NR7W",
  "age" : "Pennsylvanian",
  "formation" : "",
  "fossils" : "-",
  "comments" : "",
  "reference" : "",
  "latLong" : "https://scholarworks.iu.edu/dspace/bitstream/2022/280/1/C06.pdf"
}, {
  "location" : "Brookville",
  "county" : "Franklin",
  "state" : "Indiana",
  "directions" : "",
  "age" : "",
  "formation" : "",
  "fossils" : "Bryozoa Rhombotrypa",
  "comments" : "IN0075",
  "reference" : "Original said 'Rhomotrypa'",
  "latLong" : ""
}, {
  "location" : "Brookville",
  "county" : "Franklin",
  "state" : "Indiana",
  "directions" : "1.6lm N in roadcut on Bon Well Hill at junction of IN101 and Brookville Dam Road,39d26m13s 84d58m41s",
  "age" : "Ordovician",
  "formation" : "Oregonia|Waynesville",
  "fossils" : "Many Cincinnatian outcrops have abundant,well preserved,fossils",
  "comments" : "IN0076",
  "reference" : "Oregonia (shallow subtidal),Waynesville(Offshore)",
  "latLong" : ""
}, {
  "location" : "Brookville",
  "county" : "Franklin",
  "state" : "Indiana",
  "directions" : "8km N In roadcuts along IN101 39d29m15s 85d56m55s",
  "age" : "Ordovician",
  "formation" : "Waynesville|Whitewater|Saluda",
  "fossils" : "Many Cincinnatian outcrops have abundant,well preserved,fossils",
  "comments" : "IN0077",
  "reference" : "Waynesville (Offshore),Whitewater (Shallow subtidal),Saluda(Lagoonal)",
  "latLong" : ""
}, {
  "location" : "Brookville",
  "county" : "Franklin",
  "state" : "Indiana",
  "directions" : "In deposits along Little Cedar Creek",
  "age" : "Pleistocene",
  "formation" : "",
  "fossils" : "Mollusks,Vertigo,Pupilla,Columella,Discus.",
  "comments" : "IN0078",
  "reference" : "",
  "latLong" : ""
}, {
  "location" : "Cedar Grove",
  "county" : "Franklin",
  "state" : "Indiana",
  "directions" : "At South Gate Hill in roadcuts on IN1 3km S of US52 39d21m30sN 84d57m17sW",
  "age" : "Ordovician",
  "formation" : "Oregonia|Waynesville|Liberty|Whitewater|Saluda",
  "fossils" : "Many Cincinnatian outcrops have abundant,well preserved,fossils",
  "comments" : "IN0079",
  "reference" : "Oregonia(shallow subtidal)|Waynesville(offshore)|Liberty(deep subtidal)|Whitewater(shallow subtidal)|Saluda(lagoonal)",
  "latLong" : ""
}, {
  "location" : "Peppertown",
  "county" : "Franklin",
  "state" : "Indiana",
  "directions" : "in old roadcut 4.8km W. NW from IN 229 in Peppertown 2.72km to series of road junctions -- Left, then Right, cross Salt Creek and keep left. 1.3km and turn Right. 300m to roadcut W1/2S17T11NR12E",
  "age" : "Ordovician",
  "formation" : "",
  "fossils" : "-",
  "comments" : "",
  "reference" : "",
  "latLong" : "https://scholarworks.iu.edu/ dspace/bitstream/2022/280/1/C06.pdf"
}, {
  "location" : "St Mary's",
  "county" : "Franklin",
  "state" : "Indiana",
  "directions" : "3.2km N in roadcut",
  "age" : "Ordovician",
  "formation" : "Richmond",
  "fossils" : "Leptaena,Platystrophia,Rafinesquina,Rhynchotrema,Dalmanella,Hebertella,Byssonychia,bivalves,Cyclonema,Flexicalymene,Bryozoa",
  "comments" : "IN0080",
  "reference" : "",
  "latLong" : ""
}, {
  "location" : "Fairmount",
  "county" : "Grant",
  "state" : "Indiana",
  "directions" : "",
  "age" : "Pleistocene",
  "formation" : "",
  "fossils" : "beaver Castoroides",
  "comments" : "IN0081",
  "reference" : "",
  "latLong" : ""
}, {
  "location" : "Marion",
  "county" : "Grant",
  "state" : "Indiana",
  "directions" : "In city park along W side of Missessinewa River in bioherm",
  "age" : "Silurian",
  "formation" : "",
  "fossils" : "typical reef fossils.",
  "comments" : "IN0082",
  "reference" : "",
  "latLong" : ""
}, {
  "location" : "Mier",
  "county" : "Grant",
  "state" : "Indiana",
  "directions" : "2 km SE in abandoned quarry on Pipe Creek",
  "age" : "",
  "formation" : "",
  "fossils" : "Cladopora,Eridophyllum,Favosites,Heliolites,Zaphrentis,Conchidium,Leptaena,Rhipidomella",
  "comments" : "IN0083",
  "reference" : "Reportedly Mier is largely defunct. USGS puts Mier at 40.575N 85.826W",
  "latLong" : ""
}, {
  "location" : "Coalmont",
  "county" : "Greene",
  "state" : "Indiana",
  "directions" : "old mines 1.6km N, W of IN159 in shaly limestone S19,30T8NR7W",
  "age" : "Pennsylvanian",
  "formation" : "",
  "fossils" : "pyritized gastropods, brachiopods,bivalves, crinoid stems, petrified wood",
  "comments" : "",
  "reference" : "",
  "latLong" : "https://scholarworks.iu.edu/dspace/bitstream/2022/280/1/C06.pdf"
}, {
  "location" : "Coalmont",
  "county" : "Greene",
  "state" : "Indiana",
  "directions" : "old mines 1.6km N, W of IN159 in shaly limestone S19,30T8NR7W",
  "age" : "Pennsylvanian",
  "formation" : "",
  "fossils" : "pyritized gastropods, brachiopods,bivalves, crinoid stems, petrified wood",
  "comments" : "",
  "reference" : "",
  "latLong" : "https://scholarworks.iu.edu/dspace/bitstream/2022/280/1/C06.pdf"
}, {
  "location" : "Coalmont",
  "county" : "Greene",
  "state" : "Indiana",
  "directions" : "old mines W then N on W side of county-line road in shaly limestone S19,30T8NR7W",
  "age" : "Pennsylvanian",
  "formation" : "",
  "fossils" : "pyritized gastropods, brachiopods,bivalves, crinoid stems, petrified wood",
  "comments" : "",
  "reference" : "",
  "latLong" : "https://scholarworks.iu.edu/dspace/bitstream/2022/280/1/C06.pdf"
}, {
  "location" : "Gilmour",
  "county" : "Greene",
  "state" : "Indiana",
  "directions" : "old mines N and S of town in shaly limestone S13,18,19,24S8T8NR7W",
  "age" : "Pennsylvanian",
  "formation" : "",
  "fossils" : "pyritized gastropods, brachiopods,bivalves, crinoid stems, petrified wood",
  "comments" : "",
  "reference" : "",
  "latLong" : "https://scholarworks.iu.edu/dspace/bitstream/2022/280/1/C06.pdf"
}, {
  "location" : "Jasonville",
  "county" : "Greene",
  "state" : "Indiana",
  "directions" : "From CMSP rr crossing in Jasonville on IN 48 go 13 blocks W. S 2.4km. W across RR spur 620m W and N 480m to pit with exposed shaly limestones -- pyritized fossils SE1/4S8T8NR7W",
  "age" : "Pennsylvanian",
  "formation" : "",
  "fossils" : "pyritized gastropods, brachiopods,bivalves, crinoid stems, petrified wood",
  "comments" : "",
  "reference" : "",
  "latLong" : "https://scholarworks.iu.edu/dspace/bitstream/2022/280/1/C06.pdf"
}, {
  "location" : "Newport",
  "county" : "Greene",
  "state" : "Indiana",
  "directions" : "2 km W",
  "age" : "Mississippian",
  "formation" : "Beech Creek Limestone",
  "fossils" : "large crinoid stems,gastropods,Pentremites fragments,brachiopods",
  "comments" : "IN0084",
  "reference" : "",
  "latLong" : ""
}, {
  "location" : "Owensburg",
  "county" : "Greene",
  "state" : "Indiana",
  "directions" : "3km N near Sexson Spring",
  "age" : "Mississippian",
  "formation" : "Beech Creek Limestone",
  "fossils" : "large crinoid stems",
  "comments" : "IN0085",
  "reference" : "",
  "latLong" : ""
}, {
  "location" : "Ridgeport",
  "county" : "Greene",
  "state" : "Indiana",
  "directions" : "2 km NW nw1/4ne1/4s11t7nr4w in quarry",
  "age" : "Pennsylvanian[?]",
  "formation" : "",
  "fossils" : "crinoid stems; brachiopods: Martinia,Composita,Cleiothyridina,Echinoconchus,Productus,Linoproductus,;Bryozoa - Archimedes; blastoids - Pentremites",
  "comments" : "IN0086",
  "reference" : "There is a Birch Creek in Indiana,but the Geolex data base lists Birch Creek members/formations only in Oklahoma and Alaska",
  "latLong" : ""
}, {
  "location" : "Ridgeport",
  "county" : "Greene",
  "state" : "Indiana",
  "directions" : "600 meters NE on IN54",
  "age" : "Mississippian",
  "formation" : "Beech Creek Limestone",
  "fossils" : "crinoid stems,Archimedes,brachiopods,gastropods",
  "comments" : "IN0087",
  "reference" : "",
  "latLong" : ""
}, {
  "location" : "-",
  "county" : "Hamilton",
  "state" : "Indiana",
  "directions" : "",
  "age" : "Ordovician",
  "formation" : "Cincinnatian",
  "fossils" : "numerous fossils in limey shales",
  "comments" : "IN0090",
  "reference" : "",
  "latLong" : ""
}, {
  "location" : "Fishersburg[?]",
  "county" : "Hamilton",
  "state" : "Indiana",
  "directions" : "In bioherm",
  "age" : "Silurian",
  "formation" : "",
  "fossils" : "reef fossils",
  "comments" : "IN0088",
  "reference" : "Probably 'Fishers a.k.a. Fishers Station'",
  "latLong" : ""
}, {
  "location" : "Noblesville",
  "county" : "Hamilton",
  "state" : "Indiana",
  "directions" : "7 km NE along White River in Bioherm at Conners Mill",
  "age" : "Silurian",
  "formation" : "",
  "fossils" : "reef fossils",
  "comments" : "IN0089",
  "reference" : "",
  "latLong" : ""
}, {
  "location" : "Corydon",
  "county" : "Harrison",
  "state" : "Indiana",
  "directions" : "At Corydon Quarry at junction between Paoli Limestone and Mooretown Shale",
  "age" : "Mississippian",
  "formation" : "Paoli|Mooretown",
  "fossils" : "Fossil debris?",
  "comments" : "",
  "reference" : "Paleolist- 02/03/2008 08:19 PM",
  "latLong" : ""
}, {
  "location" : "Corydon",
  "county" : "Harrison",
  "state" : "Indiana",
  "directions" : "area exposures",
  "age" : "",
  "formation" : "",
  "fossils" : "fossils",
  "comments" : "IN0091",
  "reference" : "",
  "latLong" : ""
}, {
  "location" : "Depauw",
  "county" : "Harrison",
  "state" : "Indiana",
  "directions" : "3 km E in ditch along County road in NW1/4sw1/4s15t2sr3e",
  "age" : "Mississippian",
  "formation" : "St Genevieve Limestone",
  "fossils" : "crinoid stems",
  "comments" : "IN0092",
  "reference" : "",
  "latLong" : ""
}, {
  "location" : "Lanesville",
  "county" : "Harrison",
  "state" : "Indiana",
  "directions" : "",
  "age" : "Mississippian",
  "formation" : "Salem",
  "fossils" : "fish teeth-Chomatodus,Chromatodus,Cladodus,Ctenacanthus,Deltodus,Deltopsis,Helodus,Orodus,Psephodus,Sandalodus",
  "comments" : "IN0093",
  "reference" : "",
  "latLong" : ""
}, {
  "location" : "Bedford[?]",
  "county" : "Harrison[?]",
  "state" : "Indiana",
  "directions" : "area exposures",
  "age" : "",
  "formation" : "",
  "fossils" : "many fossils.",
  "comments" : "IN0094",
  "reference" : "It is unclear whether this is a reference to Bedford in Lawrence County or Bradford in Harrison County",
  "latLong" : ""
}, {
  "location" : "Kokomo",
  "county" : "Howard",
  "state" : "Indiana",
  "directions" : "In area quarries. Well preserved faunas",
  "age" : "Silurian",
  "formation" : "Kokomo Limestone",
  "fossils" : "algae,Ceratiocaris,Anomalocaris?,Buthotrephis,Eurypterus,Eusarcus,Stylonurus",
  "comments" : "IN0095",
  "reference" : "",
  "latLong" : ""
}, {
  "location" : "Kokomo",
  "county" : "Howard",
  "state" : "Indiana",
  "directions" : "on W. Markland Ave in quarry",
  "age" : "Silurian",
  "formation" : "Missessinewa Shale",
  "fossils" : "graptolites",
  "comments" : "IN0096",
  "reference" : "",
  "latLong" : ""
}, {
  "location" : "-",
  "county" : "Huntington",
  "state" : "Indiana",
  "directions" : "In regional bioherms",
  "age" : "Silurian",
  "formation" : "",
  "fossils" : "fossils",
  "comments" : "IN0104",
  "reference" : "",
  "latLong" : ""
}, {
  "location" : "Huntington",
  "county" : "Huntington",
  "state" : "Indiana",
  "directions" : "1 km S",
  "age" : "",
  "formation" : "",
  "fossils" : "graptolites",
  "comments" : "IN0097",
  "reference" : "",
  "latLong" : ""
}, {
  "location" : "Huntington",
  "county" : "Huntington",
  "state" : "Indiana",
  "directions" : "1.6km E on US24 from Erie RR Xing. S on N Broadway, E on Sabine Street. Fossils in Erie Stone Company Quarry SE1/4S12T28NR9E",
  "age" : "Silurian",
  "formation" : "",
  "fossils" : "Abundant moderately well preserved brachiopods and corals",
  "comments" : "",
  "reference" : "",
  "latLong" : "https://scholarworks.iu.edu/ dspace/bitstream/2022/280/1/C06.pdf"
}, {
  "location" : "Huntington",
  "county" : "Huntington",
  "state" : "Indiana",
  "directions" : "200 meters S in bioherm in quarry",
  "age" : "Silurian",
  "formation" : "",
  "fossils" : "Stromatoporoids,gastropods,brachiopods",
  "comments" : "IN0098",
  "reference" : "",
  "latLong" : ""
}, {
  "location" : "Huntington",
  "county" : "Huntington",
  "state" : "Indiana",
  "directions" : "In many area exposures",
  "age" : "",
  "formation" : "",
  "fossils" : "fossils",
  "comments" : "IN0099",
  "reference" : "",
  "latLong" : ""
}, {
  "location" : "Huntington",
  "county" : "Huntington",
  "state" : "Indiana",
  "directions" : "area quarries",
  "age" : "Silurian",
  "formation" : "Huntington dolomite",
  "fossils" : "brachiopods - Conchidium; Corals -Cladopora,Favosites,Halysites,Heliolites,Zaphrentis; bryozoa -Fenestella,trilobites",
  "comments" : "IN0100",
  "reference" : "",
  "latLong" : ""
}, {
  "location" : "Huntington",
  "county" : "Huntington",
  "state" : "Indiana",
  "directions" : "area quarries in very fossiliferous beds",
  "age" : "Silurian",
  "formation" : "Huntington",
  "fossils" : "brachiopods;Conchidium - Corals; Cladopora,Favosites,Halysites,Heliolites,Zaphrentis - Bryozoa; Fenestella - Trilobites",
  "comments" : "IN0101",
  "reference" : "",
  "latLong" : ""
}, {
  "location" : "Markle",
  "county" : "Huntington",
  "state" : "Indiana",
  "directions" : "1 km S in abandoned quarry",
  "age" : "",
  "formation" : "",
  "fossils" : "graptolites",
  "comments" : "IN0102",
  "reference" : "",
  "latLong" : ""
}, {
  "location" : "Markle",
  "county" : "Huntington",
  "state" : "Indiana",
  "directions" : "200 meters S in quarry in bioherm",
  "age" : "Silurian",
  "formation" : "",
  "fossils" : "stromatoporoids,gastropods. brachiopods",
  "comments" : "IN0103",
  "reference" : "",
  "latLong" : ""
}, {
  "location" : "Medora",
  "county" : "Jackson",
  "state" : "Indiana",
  "directions" : "In abandoned Seymour Gravel Co Quarry. W 4.8km to T 480mE on S side of road SE1/4S29T5NR3E",
  "age" : "Mississippian",
  "formation" : "",
  "fossils" : "marine fossils",
  "comments" : "",
  "reference" : "",
  "latLong" : "https://scholarworks.iu.edu/dspace/bitstream/2022/280/1/C06.pdf"
}, {
  "location" : "Rockford",
  "county" : "Jackson",
  "state" : "Indiana",
  "directions" : "",
  "age" : "Mississippian Lower",
  "formation" : "",
  "fossils" : "Ammonites-Muensteroceras",
  "comments" : "IN0105",
  "reference" : "",
  "latLong" : ""
}, {
  "location" : "New Corydon",
  "county" : "Jay",
  "state" : "Indiana",
  "directions" : "area quarries",
  "age" : "Silurian",
  "formation" : "Huntington",
  "fossils" : "Favosites,Halysites,Heliolites,Zaphrentis,Atrypa,Leptaena,Meristina,Pentamerus,Stropheodonta,Orthoceras",
  "comments" : "IN0106",
  "reference" : "",
  "latLong" : ""
}, {
  "location" : "Madison",
  "county" : "Jefferson",
  "state" : "Indiana",
  "directions" : "10 km NE at Jefferson Lake along road parallel to S side of lake",
  "age" : "Ordovician Upper",
  "formation" : "",
  "fossils" : "?",
  "comments" : "IN0107",
  "reference" : "",
  "latLong" : ""
}, {
  "location" : "Madison",
  "county" : "Jefferson",
  "state" : "Indiana",
  "directions" : "10 km NE at Jefferson Lake spillway at E end of lake",
  "age" : "Ordovician Upper",
  "formation" : "",
  "fossils" : "?",
  "comments" : "IN0108",
  "reference" : "",
  "latLong" : ""
}, {
  "location" : "Madison",
  "county" : "Jefferson",
  "state" : "Indiana",
  "directions" : "800m W of city limit in roadcut on IN56 and in exposures to the West",
  "age" : "Ordovician",
  "formation" : "Maysville",
  "fossils" : "Coral-Streptelasma;gastropods;Brachiopods-Rafinesquina;Bryozoa-Hallopora;gastropods,bivalves,cephalopods,trilobite fragments-Flexicalymene",
  "comments" : "IN0109",
  "reference" : "",
  "latLong" : ""
}, {
  "location" : "Madison",
  "county" : "Jefferson",
  "state" : "Indiana",
  "directions" : "Abundant diverse marine fossils at Clifty Falls State Park (No Collecting)",
  "age" : "Ordovician",
  "formation" : "",
  "fossils" : "-",
  "comments" : "",
  "reference" : "",
  "latLong" : "https://scholarworks.iu.edu/ dspace/bitstream/2022/280/1/C06.pdf"
}, {
  "location" : "Madison",
  "county" : "Jefferson",
  "state" : "Indiana",
  "directions" : "Abundant diverse marine fossils in Pennsylvanian RR cuts W of IN7",
  "age" : "Ordovician",
  "formation" : "",
  "fossils" : "-",
  "comments" : "",
  "reference" : "",
  "latLong" : "https://scholarworks.iu.edu/ dspace/bitstream/2022/280/1/C06.pdf"
}, {
  "location" : "Madison",
  "county" : "Jefferson",
  "state" : "Indiana",
  "directions" : "Abundant diverse marine fossils in long road cuts along IN7 N of town",
  "age" : "Ordovician",
  "formation" : "",
  "fossils" : "-",
  "comments" : "",
  "reference" : "",
  "latLong" : "https://scholarworks.iu.edu/ dspace/bitstream/2022/280/1/C06.pdf"
}, {
  "location" : "Madison",
  "county" : "Jefferson",
  "state" : "Indiana",
  "directions" : "Abundant diverse marine fossils in road cuts along IN62 opposite power plant and W of town",
  "age" : "Ordovician",
  "formation" : "",
  "fossils" : "-",
  "comments" : "",
  "reference" : "",
  "latLong" : "https://scholarworks.iu.edu/ dspace/bitstream/2022/280/1/C06.pdf"
}, {
  "location" : "Madison",
  "county" : "Jefferson",
  "state" : "Indiana",
  "directions" : "Along Riley Creek",
  "age" : "Ordovician Upper",
  "formation" : "",
  "fossils" : "?",
  "comments" : "IN0110",
  "reference" : "",
  "latLong" : ""
}, {
  "location" : "Madison",
  "county" : "Jefferson",
  "state" : "Indiana",
  "directions" : "Hairpin curve on IN421",
  "age" : "Ordovician",
  "formation" : "Maysville",
  "fossils" : "Coral-Streptelasma;gastropods;Brachiopods-Leptaena",
  "comments" : "IN0111",
  "reference" : "",
  "latLong" : ""
}, {
  "location" : "Madison",
  "county" : "Jefferson",
  "state" : "Indiana",
  "directions" : "In Pennsylvania RR cuts",
  "age" : "Ordovician Upper",
  "formation" : "",
  "fossils" : "?",
  "comments" : "IN0112",
  "reference" : "",
  "latLong" : ""
}, {
  "location" : "Madison",
  "county" : "Jefferson",
  "state" : "Indiana",
  "directions" : "Madison County,IN,area road cuts",
  "age" : "Silurian",
  "formation" : "Brassfield Limestone",
  "fossils" : "typical fossils",
  "comments" : "IN0114",
  "reference" : "",
  "latLong" : ""
}, {
  "location" : "Madison",
  "county" : "Jefferson",
  "state" : "Indiana",
  "directions" : "Madison, IN, 1 km NW at Hanging Rock on IN7",
  "age" : "Silurian",
  "formation" : "Brassfield Limestone",
  "fossils" : "typical fossils",
  "comments" : "IN0113",
  "reference" : "",
  "latLong" : ""
}, {
  "location" : "Madison",
  "county" : "Jefferson",
  "state" : "Indiana",
  "directions" : "Road cuts along IN7 in N and NW part of town",
  "age" : "Ordovician Upper",
  "formation" : "",
  "fossils" : "?",
  "comments" : "IN0115",
  "reference" : "",
  "latLong" : ""
}, {
  "location" : "Madison",
  "county" : "Jefferson",
  "state" : "Indiana",
  "directions" : "Roadcut on E side of US421 1.5km N of I56 junction 38d44m58sN 85d22m35sW",
  "age" : "Ordovician",
  "formation" : "Mount Auburn|Sunset|Oregonia|Liberty",
  "fossils" : "Many Cincinnatian outcrops have abundant,well preserved,fossils",
  "comments" : "IN0116",
  "reference" : "Mount Auburn(shallow subtidal),Sunset(deep subtidal),Oregonia(Shallow subtidal),Liberty(deep subtidal)",
  "latLong" : ""
}, {
  "location" : "Madison",
  "county" : "Jefferson",
  "state" : "Indiana",
  "directions" : "Roadcut on E side of US421 1.5km N of I56 junction 38d46m39sN 85d21m53sW",
  "age" : "Ordovician",
  "formation" : "Whitewater|Saluda",
  "fossils" : "Many Cincinnatian outcrops have abundant,well preserved,fossils",
  "comments" : "IN0117",
  "reference" : "Lower Whitewater(shallow subtidal),Saluda(Peritidal),Hitz(lagoon),Upper Whitewater(shallow subtidal)",
  "latLong" : ""
}, {
  "location" : "Madison",
  "county" : "Jefferson",
  "state" : "Indiana",
  "directions" : "deep road cut on IN62 2.9km W of entrance to Clifty Falls State Park. NE1/4S6T3NR10W in about 100m thick exposure of Ordovician and Lowest Silurian rock",
  "age" : "Ordovician-Silurian",
  "formation" : "Richmond",
  "fossils" : "abundant fossils in some layers",
  "comments" : "IN0118",
  "reference" : "",
  "latLong" : ""
}, {
  "location" : "Madison",
  "county" : "Jefferson",
  "state" : "Indiana",
  "directions" : "in road cuts N of town",
  "age" : "Ordovician",
  "formation" : "",
  "fossils" : "abundant fossils",
  "comments" : "IN0119",
  "reference" : "",
  "latLong" : ""
}, {
  "location" : "Saluda",
  "county" : "Jefferson",
  "state" : "Indiana",
  "directions" : "2 km SE on NE side of Saluda Creek",
  "age" : "Silurian",
  "formation" : "Brassfield Limestone",
  "fossils" : "typical fossils",
  "comments" : "IN0120",
  "reference" : "",
  "latLong" : ""
}, {
  "location" : "Commiskey",
  "county" : "Jennings",
  "state" : "Indiana",
  "directions" : "1 km E on Graham Creek",
  "age" : "Devonian",
  "formation" : "Jeffersonville Limestone",
  "fossils" : "corals,Spirifer,crinoid buttons.",
  "comments" : "IN0121",
  "reference" : "",
  "latLong" : ""
}, {
  "location" : "North Vernon",
  "county" : "Jennings",
  "state" : "Indiana",
  "directions" : "In road cuts,river banks and at Tunnel Mill SW1/4S11T6NR8E",
  "age" : "Silurian-Devonian",
  "formation" : "Waldron",
  "fossils" : "Good fossils in some beds",
  "comments" : "IN0122",
  "reference" : "",
  "latLong" : ""
}, {
  "location" : "Tunnel Mill",
  "county" : "Jennings",
  "state" : "Indiana",
  "directions" : "on Muscatatuck Creek in Crowley F + G area inside tunnel once used to feed water to mill,In",
  "age" : "Silurian",
  "formation" : "Waldron",
  "fossils" : "Crinoids,trilobites,brachiopods",
  "comments" : "IN0123",
  "reference" : "",
  "latLong" : ""
}, {
  "location" : "Vernon",
  "county" : "Jennings",
  "state" : "Indiana",
  "directions" : "In Tunnel at Tunnel Mill on small stream 300m W of roadcut on IN3 480m S of IN7 junction SW1/4S11T6SR8E",
  "age" : "Silurian",
  "formation" : "",
  "fossils" : "Crinoids",
  "comments" : "",
  "reference" : "SW1/4S11T6SR8E",
  "latLong" : "https://scholarworks.iu.edu/ dspace/bitstream/2022/280/1/C06.pdf"
}, {
  "location" : "Vernon",
  "county" : "Jennings",
  "state" : "Indiana",
  "directions" : "In old quarry W of roadcut on IN3 480m S of IN7 junction",
  "age" : "Silurian",
  "formation" : "",
  "fossils" : "Crinoids",
  "comments" : "",
  "reference" : "",
  "latLong" : "https://scholarworks.iu.edu/ dspace/bitstream/2022/280/1/C06.pdf"
}, {
  "location" : "Vernon",
  "county" : "Jennings",
  "state" : "Indiana",
  "directions" : "In quarry near Tunnel Mill",
  "age" : "",
  "formation" : "",
  "fossils" : "corals",
  "comments" : "IN0124",
  "reference" : "",
  "latLong" : ""
}, {
  "location" : "Wheatland",
  "county" : "Knox",
  "state" : "Indiana",
  "directions" : "3.2km W on dumps of White Ash mine N of US150 and RR tracks in shales",
  "age" : "Pennsylvanian",
  "formation" : "",
  "fossils" : "plants,petrified wood",
  "comments" : "",
  "reference" : "",
  "latLong" : "https://scholarworks.iu.edu/dspace/bitstream/2022/280/1/C06.pdf"
}, {
  "location" : "Warsaw",
  "county" : "Kosciusko",
  "state" : "Indiana",
  "directions" : "",
  "age" : "Mississippian",
  "formation" : "Keokuk Limestone",
  "fossils" : "Crinoids",
  "comments" : "IN0125",
  "reference" : "",
  "latLong" : ""
}, {
  "location" : "Bloomington",
  "county" : "Lawrence",
  "state" : "Indiana",
  "directions" : "South in limestone",
  "age" : "Paleozoic",
  "formation" : "",
  "fossils" : "fish-Ctenacanthus",
  "comments" : "IN0126",
  "reference" : "",
  "latLong" : ""
}, {
  "location" : "Bryantsville",
  "county" : "Lawrence",
  "state" : "Indiana",
  "directions" : "N in nw1/4nw1/4s25t4nr2w",
  "age" : "Mississippian",
  "formation" : "Bryantsville breccia",
  "fossils" : "Pugnoides,Platycrinus,Lithostrotion",
  "comments" : "IN0127",
  "reference" : "",
  "latLong" : ""
}, {
  "location" : "Bryantsville",
  "county" : "Lawrence",
  "state" : "Indiana",
  "directions" : "on US50",
  "age" : "Mississippian",
  "formation" : "Bryantsville breccia",
  "fossils" : "Pugnoides,Platycrinus,Lithostrotion",
  "comments" : "IN0128",
  "reference" : "",
  "latLong" : ""
}, {
  "location" : "Bryantsville",
  "county" : "Lawrence",
  "state" : "Indiana",
  "directions" : "on US50",
  "age" : "Mississippian",
  "formation" : "Bryantsville breccia",
  "fossils" : "Pugnoides,Platycrinus,Lithostrotion",
  "comments" : "IN0129",
  "reference" : "",
  "latLong" : ""
}, {
  "location" : "Bryantsville",
  "county" : "Lawrence",
  "state" : "Indiana",
  "directions" : "to E in Limestone quarries",
  "age" : "Mississippian",
  "formation" : "Bryantsville breccia",
  "fossils" : "Pugnoides,Platycrinus,Lithostrotion",
  "comments" : "IN0130",
  "reference" : "",
  "latLong" : ""
}, {
  "location" : "Silverville",
  "county" : "Lawrence",
  "state" : "Indiana",
  "directions" : "In abandoned quarry N of IN158 1.3km E NE1/4S20T5NR2W",
  "age" : "Mississippian",
  "formation" : "",
  "fossils" : "Crinoid fragments",
  "comments" : "",
  "reference" : "",
  "latLong" : "https://scholarworks.iu.edu/dspace/bitstream/2022/280/1/C06.pdf"
}, {
  "location" : "Greenbriar",
  "county" : "Madison",
  "state" : "Indiana",
  "directions" : "",
  "age" : "Mississippian",
  "formation" : "St Louis",
  "fossils" : "fish teeth/spines-Antliodus,Archaeobatis,Cladodus,Cladoselache,Deltodus,Labodus,Physonemus,Polyrhizodus,Psammodus,Sandalodus",
  "comments" : "IN0131",
  "reference" : "",
  "latLong" : ""
}, {
  "location" : "Ingalls",
  "county" : "Madison",
  "state" : "Indiana",
  "directions" : "In area quarries",
  "age" : "Silurian",
  "formation" : "Liston Creek Limestone",
  "fossils" : "abundant fossils - bryozoa",
  "comments" : "IN0132",
  "reference" : "",
  "latLong" : ""
}, {
  "location" : "Naval Surface Weapons Center",
  "county" : "Martin",
  "state" : "Indiana",
  "directions" : "RR tracks in front of Magazines 2412 and 2413 (UTM 16S ET09099 01190)",
  "age" : "Pennsylvanian",
  "formation" : "Mansfield",
  "fossils" : "ichnofossils",
  "comments" : "https://scholarworks.iu.edu/dspace/bitstream/2022/1821/1/Thesis_Simonelli_Glenn.pdf",
  "reference" : "",
  "latLong" : ""
}, {
  "location" : "Naval Surface Weapons Center",
  "county" : "Martin",
  "state" : "Indiana",
  "directions" : "near Magazine 2357 at the intersection of H383 and HR150 (UTM 16SET09444 01930)",
  "age" : "Pennsylvanian",
  "formation" : "Mansfield",
  "fossils" : "ichnofossils",
  "comments" : "https://scholarworks.iu.edu/dspace/bitstream/2022/1821/1/Thesis_Simonelli_Glenn.pdf",
  "reference" : "",
  "latLong" : ""
}, {
  "location" : "Shoals",
  "county" : "Martin",
  "state" : "Indiana",
  "directions" : "5 km NW 200 meters W of IN450 in lenses of white chert",
  "age" : "Mississippian Upper",
  "formation" : "Glen Dean",
  "fossils" : "well preserved fossils",
  "comments" : "IN0133",
  "reference" : "",
  "latLong" : ""
}, {
  "location" : "-",
  "county" : "Miami",
  "state" : "Indiana",
  "directions" : "14 bioherms scattered around county",
  "age" : "Silurian",
  "formation" : "",
  "fossils" : "corals,brachiopods,crinoids",
  "comments" : "IN0138",
  "reference" : "",
  "latLong" : ""
}, {
  "location" : "Peru",
  "county" : "Miami",
  "state" : "Indiana",
  "directions" : "1 km NW in bioherm between Missessinewa shale and Kokomo Limestone",
  "age" : "Silurian",
  "formation" : "",
  "fossils" : "corals,brachiopods,crinoids",
  "comments" : "IN0134",
  "reference" : "",
  "latLong" : ""
}, {
  "location" : "Peru",
  "county" : "Miami",
  "state" : "Indiana",
  "directions" : "2 km SW at Nickel Plate RR crossing of Little Pipe Creek in bioherm (classic locality)",
  "age" : "Silurian",
  "formation" : "",
  "fossils" : "reef fossils",
  "comments" : "IN0135",
  "reference" : "",
  "latLong" : ""
}, {
  "location" : "Peru",
  "county" : "Miami",
  "state" : "Indiana",
  "directions" : "At City Park along S bank of Wabash River in bioherm",
  "age" : "Silurian",
  "formation" : "",
  "fossils" : "reef fossils",
  "comments" : "IN0136",
  "reference" : "",
  "latLong" : ""
}, {
  "location" : "Peru",
  "county" : "Miami",
  "state" : "Indiana",
  "directions" : "on Hospital Hill on North Broadway in cuts in reef",
  "age" : "Silurian",
  "formation" : "",
  "fossils" : "reef fossils",
  "comments" : "IN0137",
  "reference" : "",
  "latLong" : ""
}, {
  "location" : "Bloomington",
  "county" : "Monroe",
  "state" : "Indiana",
  "directions" : "6 km E of IN46 / IN446 intersection",
  "age" : "Mississippian",
  "formation" : "Ramp Creek",
  "fossils" : "crinoids - mostly fragmental",
  "comments" : "IN0139",
  "reference" : "",
  "latLong" : ""
}, {
  "location" : "Bloomington",
  "county" : "Monroe",
  "state" : "Indiana",
  "directions" : "9 km E on N side of IN46 in road cut in limestones",
  "age" : "Mississippian",
  "formation" : "",
  "fossils" : "crinoid stems",
  "comments" : "IN0140",
  "reference" : "",
  "latLong" : ""
}, {
  "location" : "Bloomington",
  "county" : "Monroe",
  "state" : "Indiana",
  "directions" : "At Tinker's[?] Creek",
  "age" : "Mississippian",
  "formation" : "Bedford Limestone",
  "fossils" : "Tamiobatis",
  "comments" : "IN0141",
  "reference" : "Couldn't identify a Tinker/Tinker's Creek in Indiana",
  "latLong" : ""
}, {
  "location" : "Bloomington",
  "county" : "Monroe",
  "state" : "Indiana",
  "directions" : "IN46 east of town",
  "age" : "",
  "formation" : "",
  "fossils" : "crinoids",
  "comments" : "IN0142",
  "reference" : "",
  "latLong" : ""
}, {
  "location" : "Bloomington",
  "county" : "Monroe",
  "state" : "Indiana",
  "directions" : "In road cut on IN46 108km E on N side of road NE1/4S4T8NR1E and also in area exposures to N",
  "age" : "Mississippian",
  "formation" : "",
  "fossils" : "Crinoid fragments",
  "comments" : "",
  "reference" : "",
  "latLong" : "https://scholarworks.iu.edu/ dspace/bitstream/2022/280/1/C06.pdf"
}, {
  "location" : "Bloomington",
  "county" : "Monroe",
  "state" : "Indiana",
  "directions" : "South in Limestone",
  "age" : "Mississippian",
  "formation" : "",
  "fossils" : "corals",
  "comments" : "IN0143",
  "reference" : "",
  "latLong" : ""
}, {
  "location" : "Harrodsburg",
  "county" : "Monroe",
  "state" : "Indiana",
  "directions" : "1.6km N on secondary road. In abandoned quarry 300m W. NW1/3S20T7NR1W",
  "age" : "Mississippian",
  "formation" : "Salem",
  "fossils" : "microfossils",
  "comments" : "",
  "reference" : "",
  "latLong" : "https://scholarworks.iu.edu/dspace/bitstream/2022/280/1/C06.pdf"
}, {
  "location" : "Harrodsburg",
  "county" : "Monroe",
  "state" : "Indiana",
  "directions" : "2 km N at Cleveland quarry",
  "age" : "",
  "formation" : "Salem Limestone",
  "fossils" : "Endothyra and other small fossils",
  "comments" : "IN0144",
  "reference" : "",
  "latLong" : ""
}, {
  "location" : "Harrodsville",
  "county" : "Monroe",
  "state" : "Indiana",
  "directions" : "In outcrop with geodes on SR37. Probably 17km N of Bedford just S of Monroe Lake exit",
  "age" : "Mississippian",
  "formation" : "",
  "fossils" : "brachiopods,conularids,shark teeth,pectens,crinoid columns",
  "comments" : "IN0250",
  "reference" : "",
  "latLong" : ""
}, {
  "location" : "South of Bloomington",
  "county" : "Monroe",
  "state" : "Indiana",
  "directions" : "",
  "age" : "Mississippian",
  "formation" : "",
  "fossils" : "Archimedes",
  "comments" : "IN0146",
  "reference" : "",
  "latLong" : ""
}, {
  "location" : "-",
  "county" : "Monroe,Brown",
  "state" : "Indiana",
  "directions" : "in limestones and sandstones",
  "age" : "Mississippian",
  "formation" : "Edwardsville",
  "fossils" : "forams,crinoids,bryozoa,mollusks,arthropods,echinoderms",
  "comments" : "IN0147",
  "reference" : "",
  "latLong" : ""
}, {
  "location" : "-",
  "county" : "Montgomery",
  "state" : "Indiana",
  "directions" : "",
  "age" : "Mississippian",
  "formation" : "Edwardsville",
  "fossils" : "Crinoids",
  "comments" : "IN0154",
  "reference" : "",
  "latLong" : ""
}, {
  "location" : "-",
  "county" : "Montgomery",
  "state" : "Indiana",
  "directions" : "in creekbed exposures",
  "age" : "Mississippian",
  "formation" : "",
  "fossils" : "crinoids",
  "comments" : "IN0155",
  "reference" : "",
  "latLong" : ""
}, {
  "location" : "Crawfordsville",
  "county" : "Montgomery",
  "state" : "Indiana",
  "directions" : "",
  "age" : "Mississippian Lower",
  "formation" : "Edwardsville",
  "fossils" : "Coral-Blothrophyllum",
  "comments" : "IN0148",
  "reference" : "",
  "latLong" : ""
}, {
  "location" : "Crawfordsville",
  "county" : "Montgomery",
  "state" : "Indiana",
  "directions" : "At Corey's Bluff along W bank of Sugar Creek. 104 species of crinoids collected between 1832 and 1946. Reported to be overgrown although traces of the old diggings can be found.",
  "age" : "Mississippian",
  "formation" : "Glen Dean Limestone",
  "fossils" : "crinoids",
  "comments" : "IN0149",
  "reference" : "",
  "latLong" : ""
}, {
  "location" : "Crawfordsville",
  "county" : "Montgomery",
  "state" : "Indiana",
  "directions" : "In nests in siltstone",
  "age" : "Mississippian",
  "formation" : "Keokuk Limestone",
  "fossils" : "Crinoids,Gastropods Platyceras,Trilobites Griffithides,Crinoids - Taxocrinus,Onychocrinus,Batocrinus,Cyathocrinus,Platycrinus,Pachylocrinus,Eucatillocrinus. Many other phyla as well. Rare Ophiuroids. Gastropods - Platyceras.",
  "comments" : "IN0150",
  "reference" : "",
  "latLong" : ""
}, {
  "location" : "Crawfordsville",
  "county" : "Montgomery",
  "state" : "Indiana",
  "directions" : "N on W bank of Sugar Creek in new quarries",
  "age" : "Mississippian",
  "formation" : "Glen Dean",
  "fossils" : "Very fine crinoids",
  "comments" : "IN0151",
  "reference" : "",
  "latLong" : ""
}, {
  "location" : "New Ross",
  "county" : "Montgomery",
  "state" : "Indiana",
  "directions" : "In dumps at abandoned quarry 2.4km SW NE1/4S3T17NR3W Permission Required",
  "age" : "Mississippian",
  "formation" : "",
  "fossils" : "Crinoid fragments",
  "comments" : "",
  "reference" : "",
  "latLong" : "https://scholarworks.iu.edu/ dspace/bitstream/2022/280/1/C06.pdf"
}, {
  "location" : "Shades State Park",
  "county" : "Montgomery",
  "state" : "Indiana",
  "directions" : "At 'Beachler's Nest in a meander of Indian Creek 1 km N of IN234",
  "age" : "",
  "formation" : "",
  "fossils" : "crinoid crowns",
  "comments" : "IN0152",
  "reference" : "",
  "latLong" : ""
}, {
  "location" : "Shades State Park",
  "county" : "Montgomery",
  "state" : "Indiana",
  "directions" : "downstream on Sugar Creek near mouth of Indian Creek",
  "age" : "",
  "formation" : "",
  "fossils" : "crinoid crowns",
  "comments" : "IN0153",
  "reference" : "",
  "latLong" : ""
}, {
  "location" : "Brooklyn",
  "county" : "Morgan",
  "state" : "Indiana",
  "directions" : "",
  "age" : "",
  "formation" : "",
  "fossils" : "brachiopods",
  "comments" : "IN0251",
  "reference" : "",
  "latLong" : ""
}, {
  "location" : "Hartford",
  "county" : "Ohio",
  "state" : "Indiana",
  "directions" : "6.2km SE on county road",
  "age" : "Ordovician",
  "formation" : "Maysville",
  "fossils" : "brachiopods-Rafinesquina,Platystrophia,Hebertella,bivalves,cephalopods,Bryozoa-Hallopora",
  "comments" : "IN0157",
  "reference" : "",
  "latLong" : ""
}, {
  "location" : "Rising Sun",
  "county" : "Ohio",
  "state" : "Indiana",
  "directions" : "4.8km S on IN56 SW1/4S15T3NR1W",
  "age" : "Ordovician",
  "formation" : "",
  "fossils" : "Abundant, diverse, bryozoa",
  "comments" : "",
  "reference" : "",
  "latLong" : "https://scholarworks.iu.edu/ dspace/bitstream/2022/280/1/C06.pdf"
}, {
  "location" : "Rising Sun",
  "county" : "Ohio",
  "state" : "Indiana",
  "directions" : "4.8km S on hillside SW of junction of IN56 and IN156",
  "age" : "Ordovician",
  "formation" : "Eden",
  "fossils" : "Brachiopods-Dalmanella,Sowerbyella;Bryozoa,Graptolites-Climacograptus;trilobite fragments-Cryptolithus",
  "comments" : "IN0158",
  "reference" : "",
  "latLong" : ""
}, {
  "location" : "French Lick",
  "county" : "Orange",
  "state" : "Indiana",
  "directions" : "4.5 km SE 200 meters NW of road fork",
  "age" : "Mississippian",
  "formation" : "Beech Creek Limestone",
  "fossils" : "abundant crinoid stems,brachiopods,some gastropods",
  "comments" : "IN0159",
  "reference" : "",
  "latLong" : ""
}, {
  "location" : "Paoli",
  "county" : "Orange",
  "state" : "Indiana",
  "directions" : "West in quarry to N of abandoned RR station sw1/4se1/4se1/4s35t2nr1w",
  "age" : "Mississippian",
  "formation" : "Paoli",
  "fossils" : "?",
  "comments" : "IN0160",
  "reference" : "",
  "latLong" : ""
}, {
  "location" : "Paoli",
  "county" : "Orange",
  "state" : "Indiana",
  "directions" : "area exposures",
  "age" : "Mississippian",
  "formation" : "Paoli",
  "fossils" : "?",
  "comments" : "IN0161",
  "reference" : "",
  "latLong" : ""
}, {
  "location" : "Prospect",
  "county" : "Orange",
  "state" : "Indiana",
  "directions" : "4 km N 50 meters SW of road at head of Stillhouse Hollow",
  "age" : "",
  "formation" : "",
  "fossils" : "crinoid stems. brachiopods,gastropods",
  "comments" : "IN0162",
  "reference" : "",
  "latLong" : ""
}, {
  "location" : "Atkinsonville",
  "county" : "Owen",
  "state" : "Indiana",
  "directions" : "2 km N. 200 meters S of old road",
  "age" : "",
  "formation" : "",
  "fossils" : "crinoid stems,brachiopods,gastropods",
  "comments" : "IN0163",
  "reference" : "",
  "latLong" : ""
}, {
  "location" : "Freedom",
  "county" : "Owen",
  "state" : "Indiana",
  "directions" : "1 km W",
  "age" : "Mississippian",
  "formation" : "Beech Creek Limestone",
  "fossils" : "Archimedes,tetracorals,crinoid stems",
  "comments" : "IN0164",
  "reference" : "",
  "latLong" : ""
}, {
  "location" : "Gosport",
  "county" : "Owen",
  "state" : "Indiana",
  "directions" : "",
  "age" : "Mississippian",
  "formation" : "Warsaw",
  "fossils" : "Shark teeth-Sandalodus",
  "comments" : "IN0165",
  "reference" : "",
  "latLong" : ""
}, {
  "location" : "Spencer",
  "county" : "Owen",
  "state" : "Indiana",
  "directions" : "",
  "age" : "Mississippian",
  "formation" : "St Louis",
  "fossils" : "fish teeth/spines-Antliodus",
  "comments" : "IN0166",
  "reference" : "",
  "latLong" : ""
}, {
  "location" : "Spencer",
  "county" : "Owen",
  "state" : "Indiana",
  "directions" : "Occasional fossils in large quarry 1.6km S on W side I67 NE1/4S30T10NR3W",
  "age" : "Mississippian",
  "formation" : "",
  "fossils" : "Brachiopods,Corals",
  "comments" : "",
  "reference" : "",
  "latLong" : "https://scholarworks.iu.edu/ dspace/bitstream/2022/280/1/C06.pdf"
}, {
  "location" : "Logan Quarry",
  "county" : "Parke",
  "state" : "Indiana",
  "directions" : "Near Sugar Creek",
  "age" : "Mississippian",
  "formation" : "Mecca Quarry Shale",
  "fossils" : "Fish",
  "comments" : "IN0167",
  "reference" : "May be Pennsylvanian",
  "latLong" : ""
}, {
  "location" : "Mecca",
  "county" : "Parke",
  "state" : "Indiana",
  "directions" : "In area quarries",
  "age" : "",
  "formation" : "",
  "fossils" : "fossil fish",
  "comments" : "IN0168",
  "reference" : "",
  "latLong" : ""
}, {
  "location" : "Montezuma",
  "county" : "Parke",
  "state" : "Indiana",
  "directions" : "5.6km SE",
  "age" : "Pennsylvanian",
  "formation" : "",
  "fossils" : "Vertebrates-Listracanthus,Petrodus",
  "comments" : "IN0169",
  "reference" : "",
  "latLong" : ""
}, {
  "location" : "Reserve Township",
  "county" : "Parke",
  "state" : "Indiana",
  "directions" : "",
  "age" : "Pennsylvanian",
  "formation" : "Staunton",
  "fossils" : "sharks - Orodus",
  "comments" : "IN0170",
  "reference" : "",
  "latLong" : ""
}, {
  "location" : "Reserve Township",
  "county" : "Parke",
  "state" : "Indiana",
  "directions" : "Logan Quarry in shale",
  "age" : "Pennsylvanian",
  "formation" : "Staunton",
  "fossils" : "Symmorium",
  "comments" : "IN0171",
  "reference" : "",
  "latLong" : ""
}, {
  "location" : "Wabash Township",
  "county" : "Parke",
  "state" : "Indiana",
  "directions" : "600m N of SW corner of S18T15NR8 on Hessler property",
  "age" : "Mississippian",
  "formation" : "Mecca Quarry Shale",
  "fossils" : "Fish",
  "comments" : "IN0172",
  "reference" : "",
  "latLong" : ""
}, {
  "location" : "Branchville",
  "county" : "Perry",
  "state" : "Indiana",
  "directions" : "1 km E in abandoned quarry",
  "age" : "Mississippian",
  "formation" : "Glen dean Limestone",
  "fossils" : "fenestrate bryozoa",
  "comments" : "IN0173",
  "reference" : "",
  "latLong" : ""
}, {
  "location" : "Branchville",
  "county" : "Perry",
  "state" : "Indiana",
  "directions" : "1kmE and 160m N of road. In abandoned Lutring and Sons quarry in shaly limestone and black shale",
  "age" : "Mississippian",
  "formation" : "",
  "fossils" : "crinoids,other fossils",
  "comments" : "",
  "reference" : "",
  "latLong" : "https://scholarworks.iu.edu/dspace/bitstream/2022/280/1/C06.pdf"
}, {
  "location" : "Derby",
  "county" : "Perry",
  "state" : "Indiana",
  "directions" : "1.5 km W in abandoned quarry",
  "age" : "Mississippian",
  "formation" : "Glen Dean Limestone",
  "fossils" : "Pentremites,bryozoa,crinoids,trilobite pygidia,brachiopods",
  "comments" : "IN0174",
  "reference" : "",
  "latLong" : ""
}, {
  "location" : "Leopold",
  "county" : "Perry",
  "state" : "Indiana",
  "directions" : "2.5 km E in quarry",
  "age" : "",
  "formation" : "",
  "fossils" : "fenestrate bryozoa",
  "comments" : "IN0175",
  "reference" : "",
  "latLong" : ""
}, {
  "location" : "Tobinsport",
  "county" : "Perry",
  "state" : "Indiana",
  "directions" : "2 km NE in abandoned Limestone quarry",
  "age" : "",
  "formation" : "",
  "fossils" : "Archimedes",
  "comments" : "IN0176",
  "reference" : "",
  "latLong" : ""
}, {
  "location" : "Augusta",
  "county" : "Pike",
  "state" : "Indiana",
  "directions" : "3.2km E in abandoned strip mines S14,23T2SR8W",
  "age" : "Pennsylvanian",
  "formation" : "",
  "fossils" : "brachiopods, crinoid stems, gastropods, bivalves,plant fossils",
  "comments" : "",
  "reference" : "",
  "latLong" : "https://scholarworks.iu.edu/dspace/bitstream/2022/280/1/C06.pdf"
}, {
  "location" : "Cato",
  "county" : "Pike",
  "state" : "Indiana",
  "directions" : "N and S of IN56 in abandoned strip mines S10,15,17,20T1SR7W",
  "age" : "Pennsylvanian",
  "formation" : "",
  "fossils" : "brachiopods, crinoid stems, gastropods, bivalves,plant fossils",
  "comments" : "",
  "reference" : "",
  "latLong" : "https://scholarworks.iu.edu/dspace/bitstream/2022/280/1/C06.pdf"
}, {
  "location" : "Petersburg",
  "county" : "Pike",
  "state" : "Indiana",
  "directions" : "4.5km SW on IN57 in abandoned strip mine to right of road at sharp right turn in highway in nodules N1/2S9T1SR8W",
  "age" : "Pennsylvanian",
  "formation" : "",
  "fossils" : "plant fossils",
  "comments" : "",
  "reference" : "",
  "latLong" : "https://scholarworks.iu.edu/dspace/bitstream/2022/280/1/C06.pdf"
}, {
  "location" : "Petersburg",
  "county" : "Pike",
  "state" : "Indiana",
  "directions" : "4km NE on IN57km SW on IN57 and W at Lick Creek School and Church. 300m W in old Min Win mine. Access Road 300m S of School",
  "age" : "Pennsylvanian",
  "formation" : "",
  "fossils" : "brachiopods, crinoid stems, gastropods, bivalves,plant fossils",
  "comments" : "",
  "reference" : "",
  "latLong" : "https://scholarworks.iu.edu/dspace/bitstream/2022/280/1/C06.pdf"
}, {
  "location" : "Pikesville",
  "county" : "Pike",
  "state" : "Indiana",
  "directions" : "3.2km SW in abandoned strip mines S26,35T2SR7W",
  "age" : "Pennsylvanian",
  "formation" : "",
  "fossils" : "brachiopods, crinoid stems, gastropods, bivalves,plant fossils",
  "comments" : "",
  "reference" : "",
  "latLong" : "https://scholarworks.iu.edu/dspace/bitstream/2022/280/1/C06.pdf"
}, {
  "location" : "Spurgeon",
  "county" : "Pike",
  "state" : "Indiana",
  "directions" : "In area exposures from NW around to E of town in abandoned strip mines T3SR7W and T3SR8W",
  "age" : "Pennsylvanian",
  "formation" : "",
  "fossils" : "brachiopods, crinoid stems, gastropods, bivalves,plant fossils",
  "comments" : "",
  "reference" : "",
  "latLong" : "https://scholarworks.iu.edu/dspace/bitstream/2022/280/1/C06.pdf"
}, {
  "location" : "Velpin",
  "county" : "Pike",
  "state" : "Indiana",
  "directions" : "At Walnut Grove Cemetary",
  "age" : "Devonian?",
  "formation" : "Mecca Quarry Shale",
  "fossils" : "fish-Promexyele",
  "comments" : "IN0177",
  "reference" : "",
  "latLong" : ""
}, {
  "location" : "Winslow",
  "county" : "Pike",
  "state" : "Indiana",
  "directions" : "1.6km N in abandoned strip mines S29,32T1SR7W",
  "age" : "Pennsylvanian",
  "formation" : "",
  "fossils" : "brachiopods, crinoid stems, gastropods, bivalves,plant fossils",
  "comments" : "",
  "reference" : "",
  "latLong" : "https://scholarworks.iu.edu/dspace/bitstream/2022/280/1/C06.pdf"
}, {
  "location" : "Winslow",
  "county" : "Pike",
  "state" : "Indiana",
  "directions" : "3.2km NW along Hosmer Rd in abandoned strip mines S25,26T1SR8W",
  "age" : "Pennsylvanian",
  "formation" : "",
  "fossils" : "brachiopods, crinoid stems, gastropods, bivalves,plant fossils",
  "comments" : "",
  "reference" : "",
  "latLong" : "https://scholarworks.iu.edu/dspace/bitstream/2022/280/1/C06.pdf"
}, {
  "location" : "West Franklin",
  "county" : "Posey",
  "state" : "Indiana",
  "directions" : "In Ohio River Bluff E of town in limestone ledges and black shales S1/2S24T7SR12W",
  "age" : "Pennsylvanian",
  "formation" : "",
  "fossils" : "brachiopods,gastropods,corals,Microfossils",
  "comments" : "",
  "reference" : "",
  "latLong" : "https://scholarworks.iu.edu/dspace/bitstream/2022/280/1/C06.pdf"
}, {
  "location" : "Putnamville",
  "county" : "Putnam",
  "state" : "Indiana",
  "directions" : "",
  "age" : "",
  "formation" : "",
  "fossils" : "Bryozoa Fenestella",
  "comments" : "IN0178",
  "reference" : "",
  "latLong" : ""
}, {
  "location" : "Ridgeville",
  "county" : "Randolph",
  "state" : "Indiana",
  "directions" : "SE in H+R Stone Co Quarry",
  "age" : "Silurian",
  "formation" : "Huntington",
  "fossils" : "Pentamerus",
  "comments" : "IN0179",
  "reference" : "",
  "latLong" : ""
}, {
  "location" : "Cross Plains",
  "county" : "Ripley",
  "state" : "Indiana",
  "directions" : "about 3 km N just N of I62 along Wilson's Creek for 300 meters",
  "age" : "Ordovician Upper",
  "formation" : "",
  "fossils" : "excellent fossils.",
  "comments" : "IN0180",
  "reference" : "",
  "latLong" : ""
}, {
  "location" : "Milan",
  "county" : "Ripley",
  "state" : "Indiana",
  "directions" : "6.1km S in area road and stream cuts (e.g. IN101)",
  "age" : "Ordovician",
  "formation" : "Richmond",
  "fossils" : "Brachiopods,corals,gastropods,bivalves,trilobites",
  "comments" : "IN0181",
  "reference" : "",
  "latLong" : ""
}, {
  "location" : "Osgood",
  "county" : "Ripley",
  "state" : "Indiana",
  "directions" : "4 km N",
  "age" : "Silurian",
  "formation" : "Brassfield Limestone",
  "fossils" : "Anthozoa,stromatoporoids,bryozoa,brachiopods,cephalopods,trilobites",
  "comments" : "IN0182",
  "reference" : "",
  "latLong" : ""
}, {
  "location" : "Versailles",
  "county" : "Ripley",
  "state" : "Indiana",
  "directions" : "",
  "age" : "",
  "formation" : "",
  "fossils" : "Bryozoa-Dictyospongia",
  "comments" : "IN0183",
  "reference" : "",
  "latLong" : ""
}, {
  "location" : "Versailles",
  "county" : "Ripley",
  "state" : "Indiana",
  "directions" : "",
  "age" : "Ordovician",
  "formation" : "",
  "fossils" : "Brachiopods -Sowerbyella,Hebertella",
  "comments" : "IN0184",
  "reference" : "",
  "latLong" : ""
}, {
  "location" : "Versailles",
  "county" : "Ripley",
  "state" : "Indiana",
  "directions" : "Cedar Creek,North Branch,North Branch In area exposures of",
  "age" : "Ordovician",
  "formation" : "Waynesville",
  "fossils" : "Edrioasteroids Streptaster.",
  "comments" : "IN0185",
  "reference" : "",
  "latLong" : ""
}, {
  "location" : "Versailles",
  "county" : "Ripley",
  "state" : "Indiana",
  "directions" : "In E part of town in road cuts on US 50 and in Laughery Creek",
  "age" : "Ordovician Upper",
  "formation" : "",
  "fossils" : "abundant fossils.",
  "comments" : "IN0186",
  "reference" : "",
  "latLong" : ""
}, {
  "location" : "Versailles",
  "county" : "Ripley",
  "state" : "Indiana",
  "directions" : "In quarries on Laughery Creek",
  "age" : "Ordovician",
  "formation" : "",
  "fossils" : "trilobites and brachiopods",
  "comments" : "IN0187",
  "reference" : "",
  "latLong" : ""
}, {
  "location" : "Blocher",
  "county" : "Scott",
  "state" : "Indiana",
  "directions" : "In Scott Stone Co quarry",
  "age" : "",
  "formation" : "",
  "fossils" : "corals - solitary and colonial.",
  "comments" : "IN0188",
  "reference" : "",
  "latLong" : ""
}, {
  "location" : "St Paul",
  "county" : "Shelby",
  "state" : "Indiana",
  "directions" : "S from St Paul on secondary Rd along creek. Right at road junction 800m S. 1.6km in road cut NE1/4S8T11NR8E",
  "age" : "Silurian",
  "formation" : "",
  "fossils" : "-",
  "comments" : "",
  "reference" : "",
  "latLong" : "https://scholarworks.iu.edu/ dspace/bitstream/2022/280/1/C06.pdf"
}, {
  "location" : "Waldron",
  "county" : "Shelby",
  "state" : "Indiana",
  "directions" : "",
  "age" : "Silurian",
  "formation" : "",
  "fossils" : "brachiopods -Rhynchotrema,Eospirifer,Crinoids -- Eucalyptocrinites,Blastoids Eucalyptocrinites",
  "comments" : "IN0189",
  "reference" : "",
  "latLong" : ""
}, {
  "location" : "Waldron",
  "county" : "Shelby",
  "state" : "Indiana",
  "directions" : "In Quarry spoil heaps between Conns and Deer Creeks near their confluence 2.5 km S of Waldron",
  "age" : "Silurian",
  "formation" : "Waldron",
  "fossils" : "Dalmanites,Calymene,Trimerus. Cheirurus,Otarion",
  "comments" : "IN0190",
  "reference" : "",
  "latLong" : ""
}, {
  "location" : "Waldron",
  "county" : "Shelby",
  "state" : "Indiana",
  "directions" : "at Clifty Creek",
  "age" : "Silurian",
  "formation" : "Waldron",
  "fossils" : "?",
  "comments" : "IN0191",
  "reference" : "",
  "latLong" : ""
}, {
  "location" : "Waldron",
  "county" : "Shelby",
  "state" : "Indiana",
  "directions" : "at Cook Creek",
  "age" : "Silurian",
  "formation" : "Waldron",
  "fossils" : "?",
  "comments" : "IN0192",
  "reference" : "",
  "latLong" : ""
}, {
  "location" : "Waldron",
  "county" : "Shelby",
  "state" : "Indiana",
  "directions" : "at Old Quarry",
  "age" : "Silurian",
  "formation" : "Waldron",
  "fossils" : "?",
  "comments" : "IN0193",
  "reference" : "",
  "latLong" : ""
}, {
  "location" : "Bufalloville",
  "county" : "Spencer",
  "state" : "Indiana",
  "directions" : "In abandoned coal pits in area e.g. 400m N and 1km W on both sides of road NW1/4S9T5SR5W",
  "age" : "Pennsylvanian",
  "formation" : "",
  "fossils" : "brachiopods,ostracods",
  "comments" : "",
  "reference" : "",
  "latLong" : "https://scholarworks.iu.edu/dspace/bitstream/2022/280/1/C06.pdf"
}, {
  "location" : "Florence",
  "county" : "Switzerland",
  "state" : "Indiana",
  "directions" : "3.2km NE in streamcut on IN156",
  "age" : "Ordovician",
  "formation" : "Eden",
  "fossils" : "Brachiopods-Dalmanella,Sowerbyella;Bryozoa;trilobite fragments-Cryptolithus",
  "comments" : "IN0194",
  "reference" : "",
  "latLong" : ""
}, {
  "location" : "Mount Sterling",
  "county" : "Switzerland",
  "state" : "Indiana",
  "directions" : "4km W in roadcut on county road on Smith Ridge",
  "age" : "Ordovician",
  "formation" : "Maysville",
  "fossils" : "Bryozoa-Hallopora;Brachiopods-Rafinesquina,Platystrophia,Hebertella;bivalves;gastropods-Cyclonema;cephalopod fragments",
  "comments" : "IN0195",
  "reference" : "",
  "latLong" : ""
}, {
  "location" : "Vevay",
  "county" : "Switzerland",
  "state" : "Indiana",
  "directions" : "",
  "age" : "Ordovician",
  "formation" : "",
  "fossils" : "brachiopods -Hebertella",
  "comments" : "IN0196",
  "reference" : "",
  "latLong" : ""
}, {
  "location" : "West Point",
  "county" : "Tippecanoe",
  "state" : "Indiana",
  "directions" : "2 km SE in soft siliceous shales on main branch of Flint creek",
  "age" : "",
  "formation" : "",
  "fossils" : "Nautilus,Spirifer,Productus,Discina,Terebratula,Lingula",
  "comments" : "IN0197",
  "reference" : "",
  "latLong" : ""
}, {
  "location" : "West Point",
  "county" : "Tippecanoe",
  "state" : "Indiana",
  "directions" : "400 meters NE in Limestone in back of cemetery",
  "age" : "",
  "formation" : "",
  "fossils" : "Nautilus,Spirifer,Productus,Discina,Terebratula,Lingula",
  "comments" : "IN0198",
  "reference" : "",
  "latLong" : ""
}, {
  "location" : "Brownsville",
  "county" : "Union",
  "state" : "Indiana",
  "directions" : "2 km SE of RR station in soft blue clay in ravine",
  "age" : "",
  "formation" : "Hudson River",
  "fossils" : "Well preserved Calymene",
  "comments" : "IN0199",
  "reference" : "",
  "latLong" : ""
}, {
  "location" : "Liberty",
  "county" : "Union",
  "state" : "Indiana",
  "directions" : "800m W on IN44, Turn left. Cross aSilver Creek. Turn North and park. Fossils are in Stream E of road NW1/4S11T11NR2W",
  "age" : "Ordovician",
  "formation" : "",
  "fossils" : "Corals,brachiopods,bryozoa",
  "comments" : "",
  "reference" : "",
  "latLong" : "https://scholarworks.iu.edu/ dspace/bitstream/2022/280/1/C06.pdf"
}, {
  "location" : "Liberty",
  "county" : "Union",
  "state" : "Indiana",
  "directions" : "On IN101 between Liberty and Brookville in roadcuts",
  "age" : "Ordovician",
  "formation" : "Richmond",
  "fossils" : "abundant fossils,Flexicalymene",
  "comments" : "IN0200",
  "reference" : "",
  "latLong" : ""
}, {
  "location" : "Liberty",
  "county" : "Union",
  "state" : "Indiana",
  "directions" : "area quarries",
  "age" : "",
  "formation" : "",
  "fossils" : "Well preserved trilobites",
  "comments" : "IN0201",
  "reference" : "",
  "latLong" : ""
}, {
  "location" : "Liberty",
  "county" : "Union",
  "state" : "Indiana",
  "directions" : "in road cuts near Brookville Lake",
  "age" : "Ordovician",
  "formation" : "Dillsboro",
  "fossils" : "crinoids,trilobites,etc",
  "comments" : "IN0202",
  "reference" : "",
  "latLong" : ""
}, {
  "location" : "Liberty",
  "county" : "Union",
  "state" : "Indiana",
  "directions" : "in road cuts on IN101 between Liberty and Brookville",
  "age" : "Ordovician",
  "formation" : "Dillsboro",
  "fossils" : "crinoids,trilobites,etc",
  "comments" : "IN0203",
  "reference" : "",
  "latLong" : ""
}, {
  "location" : "Liberty",
  "county" : "Union",
  "state" : "Indiana",
  "directions" : "on Hannah's Creek (Hannah's Creek runs WSW from Roseburg to Brookville Lake)",
  "age" : "",
  "formation" : "",
  "fossils" : "Well preserved trilobites",
  "comments" : "IN0204",
  "reference" : "",
  "latLong" : ""
}, {
  "location" : "Evansville",
  "county" : "Vanderburgh",
  "state" : "Indiana",
  "directions" : "At intersection of IN37 and IN64 in large road cut",
  "age" : "",
  "formation" : "",
  "fossils" : "abundant brachiopods,blastoids. A few trilobites.",
  "comments" : "IN0205",
  "reference" : "",
  "latLong" : ""
}, {
  "location" : "Evansville",
  "county" : "Vanderburgh",
  "state" : "Indiana",
  "directions" : "In ledges on E side of US460 near Mesker Park Zoo",
  "age" : "Pennsylvanian",
  "formation" : "",
  "fossils" : "brachiopods,gastropods,corals,Microfossils",
  "comments" : "",
  "reference" : "",
  "latLong" : "https://scholarworks.iu.edu/dspace/bitstream/2022/280/1/C06.pdf"
}, {
  "location" : "Evansville",
  "county" : "Vanderburgh",
  "state" : "Indiana",
  "directions" : "in area outcrops",
  "age" : "Pennsylvanian",
  "formation" : "",
  "fossils" : "Pecopteris,Neuropteris,Calamites",
  "comments" : "IN0206",
  "reference" : "",
  "latLong" : ""
}, {
  "location" : "Stacer",
  "county" : "Vanderburgh",
  "state" : "Indiana",
  "directions" : "In abandoned quarry 2.1km E S of county road SW1/4S22T4SR10W",
  "age" : "Pennsylvanian",
  "formation" : "",
  "fossils" : "brachiopods,gastropods,corals,Microfossils",
  "comments" : "",
  "reference" : "",
  "latLong" : "https://scholarworks.iu.edu/dspace/bitstream/2022/280/1/C06.pdf"
}, {
  "location" : "Newport",
  "county" : "Vermillion",
  "state" : "Indiana",
  "directions" : "At Mooreheads mine (Location unknown)",
  "age" : "Pennsylvanian",
  "formation" : "",
  "fossils" : "Vertebrates-Edestus",
  "comments" : "IN0207",
  "reference" : "",
  "latLong" : ""
}, {
  "location" : "Newport",
  "county" : "Vermillion",
  "state" : "Indiana",
  "directions" : "Roadcut on N side of KY371 (Orphanage Rd) 1km W of KY17 39d01m47sN 84d32m30sW",
  "age" : "Ordovician",
  "formation" : "Kope",
  "fossils" : "Many Cincinnatian outcrops have abundant,well preserved,fossils",
  "comments" : "IN0208",
  "reference" : "Kope (offshore)",
  "latLong" : ""
}, {
  "location" : "Vermillion County",
  "county" : "Vermillion",
  "state" : "Indiana",
  "directions" : "area exposures",
  "age" : "Pennsylvanian",
  "formation" : "Des Moines",
  "fossils" : "pelecypods.",
  "comments" : "IN0209",
  "reference" : "",
  "latLong" : ""
}, {
  "location" : "Blackhawk",
  "county" : "Vigo",
  "state" : "Indiana",
  "directions" : "In abandoned strip mines on both side of IN159 between Blackhawk and Riley in Limestones",
  "age" : "Pennsylvanian",
  "formation" : "",
  "fossils" : "brachiopods,crinoid fragments",
  "comments" : "",
  "reference" : "",
  "latLong" : "https://scholarworks.iu.edu/dspace/bitstream/2022/280/1/C06.pdf"
}, {
  "location" : "Terre Haute",
  "county" : "Vigo",
  "state" : "Indiana",
  "directions" : "At Fowler Park in nodules",
  "age" : "Pennsylvanian",
  "formation" : "",
  "fossils" : "insects,probably plants",
  "comments" : "IN0210",
  "reference" : "",
  "latLong" : ""
}, {
  "location" : "Vigo County",
  "county" : "Vigo",
  "state" : "Indiana",
  "directions" : "",
  "age" : "",
  "formation" : "",
  "fossils" : "Fern Fossils",
  "comments" : "IN0211",
  "reference" : "",
  "latLong" : ""
}, {
  "location" : "Youngstown",
  "county" : "Vigo",
  "state" : "Indiana",
  "directions" : "In Diverse Pennsylvanian fossils in",
  "age" : "Pennsylvanian",
  "formation" : "",
  "fossils" : "ironstone concretions",
  "comments" : "IN0212",
  "reference" : "",
  "latLong" : ""
}, {
  "location" : "Youngstown",
  "county" : "Vigo",
  "state" : "Indiana",
  "directions" : "In shales and walnut sized nodules on dumps of Maumee Chieftain Mine. 1.6km S on US41, E 3.2km, S, Right fork after 600m. 800m to fossil beds",
  "age" : "Pennsylvanian",
  "formation" : "",
  "fossils" : "plant fossils",
  "comments" : "",
  "reference" : "",
  "latLong" : "https://scholarworks.iu.edu/dspace/bitstream/2022/280/1/C06.pdf"
}, {
  "location" : "Youngstown",
  "county" : "Vigo",
  "state" : "Indiana",
  "directions" : "about 15 km S of Terra Haute,E of US41 in abandoned strip mines",
  "age" : "Pennsylvanian",
  "formation" : "",
  "fossils" : "Mazon Creek type fossils in nodules",
  "comments" : "IN0213",
  "reference" : "",
  "latLong" : ""
}, {
  "location" : "RichValley",
  "county" : "Wabash",
  "state" : "Indiana",
  "directions" : "",
  "age" : "Silurian",
  "formation" : "Liston Creek",
  "fossils" : "Trilobites Calymene",
  "comments" : "IN0214",
  "reference" : "",
  "latLong" : ""
}, {
  "location" : "Wabash",
  "county" : "Wabash",
  "state" : "Indiana",
  "directions" : "",
  "age" : "",
  "formation" : "",
  "fossils" : "Cephalopods - Bickmorites",
  "comments" : "IN0215",
  "reference" : "",
  "latLong" : ""
}, {
  "location" : "West Lebanon",
  "county" : "Warren",
  "state" : "Indiana",
  "directions" : "7 km S along Hwy 63 in creek tributary to Redwood Creek at second Bridge. In Limestone and overlying shales",
  "age" : "Pennsylvanian",
  "formation" : "",
  "fossils" : "Trilobites -- Ditomopyge,brachiopods.",
  "comments" : "IN0216",
  "reference" : "",
  "latLong" : ""
}, {
  "location" : "West Lebanon",
  "county" : "Warren",
  "state" : "Indiana",
  "directions" : "Complete trilobites in bank of local creek. Reported to have been dug out completely by collectors.",
  "age" : "",
  "formation" : "",
  "fossils" : "?",
  "comments" : "IN0217",
  "reference" : "",
  "latLong" : ""
}, {
  "location" : "West Lebanon",
  "county" : "Warren",
  "state" : "Indiana",
  "directions" : "small exposure in W bronch of stream cut adjacent to IN63 5.9km S (480m W of Redwood Creek) in shales and limestones NE1/4S2T20NR9W",
  "age" : "Pennsylvanian",
  "formation" : "",
  "fossils" : "brachiopods,corals,crinoid stems,protozoa,ostracods",
  "comments" : "",
  "reference" : "",
  "latLong" : "https://scholarworks.iu.edu/dspace/bitstream/2022/280/1/C06.pdf"
}, {
  "location" : "Boonville",
  "county" : "Warrick",
  "state" : "Indiana",
  "directions" : "3.2km N on IN61 and 320M W in pit of Sunlight Coal Company. SW1/4S13T5SR8W",
  "age" : "Pennsylvanian?",
  "formation" : "",
  "fossils" : "Marine fossils",
  "comments" : "",
  "reference" : "",
  "latLong" : "https://scholarworks.iu.edu/dspace/bitstream/2022/280/1/C06.pdf"
}, {
  "location" : "Boonville",
  "county" : "Warrick",
  "state" : "Indiana",
  "directions" : "4.8 km N on IN61. Turn W. 320m W to dumps N of road In abandoned Quality Coal Co mine",
  "age" : "Pennsylvanian",
  "formation" : "",
  "fossils" : "Plant fossils",
  "comments" : "",
  "reference" : "",
  "latLong" : "https://scholarworks.iu.edu/dspace/bitstream/2022/280/1/C06.pdf"
}, {
  "location" : "Boonville",
  "county" : "Warrick",
  "state" : "Indiana",
  "directions" : "Within a km or two either side of a line from Boonville to Scalesville-Yankeetown in limestones in old coal pits",
  "age" : "Pennsylvanian?",
  "formation" : "",
  "fossils" : "Marine fossils",
  "comments" : "",
  "reference" : "",
  "latLong" : "https://scholarworks.iu.edu/dspace/bitstream/2022/280/1/C06.pdf"
}, {
  "location" : "Canton",
  "county" : "Washington",
  "state" : "Indiana",
  "directions" : "In area creek banks in grayish argillaceous Limestone",
  "age" : "",
  "formation" : "",
  "fossils" : "Productus,Spirifera,Orthis,Saphiocrinus,Platycrinus,Batocrinus,Dorrycrinus,Agaricocrinus",
  "comments" : "IN0218",
  "reference" : "'Saphiocrinus' may be misspelled although it did get a single Google hit listing several species.",
  "latLong" : ""
}, {
  "location" : "Harristown",
  "county" : "Washington",
  "state" : "Indiana",
  "directions" : "S st RR cut next to secondary road to IN160 in Spergen Hill bed S1/2S24T2NR4E",
  "age" : "Mississippian",
  "formation" : "",
  "fossils" : "diverse depauperate fauna -- gastropods, others",
  "comments" : "",
  "reference" : "",
  "latLong" : "https://scholarworks.iu.edu/dspace/bitstream/2022/280/1/C06.pdf"
}, {
  "location" : "New Philadelphia",
  "county" : "Washington",
  "state" : "Indiana",
  "directions" : "2 km N and 400 meters E of Little York Road in Limestone",
  "age" : "",
  "formation" : "",
  "fossils" : "Spirifera,Granatocrinus,Batocrinus,Actinocrinus",
  "comments" : "IN0219",
  "reference" : "",
  "latLong" : ""
}, {
  "location" : "New Philadelphia",
  "county" : "Washington",
  "state" : "Indiana",
  "directions" : "along bluffs on S fork of Blue River",
  "age" : "Mississippian Lower",
  "formation" : "Burlington Limestone",
  "fossils" : "Productus,Spirifera,Batocrinus,Granatocrinus",
  "comments" : "IN0220",
  "reference" : "",
  "latLong" : ""
}, {
  "location" : "Paynter's[?] Hill",
  "county" : "Washington",
  "state" : "Indiana",
  "directions" : "",
  "age" : "Mississippian",
  "formation" : "Salem",
  "fossils" : "fish teeth-Desmiodus,Petalodus",
  "comments" : "IN0221",
  "reference" : "Can't identify a Paynter's Hill,but there is a Paynter's Cemetary 3km SSE of Salem",
  "latLong" : ""
}, {
  "location" : "Salem",
  "county" : "Washington",
  "state" : "Indiana",
  "directions" : "7 km S at Paynter's Hill[?]",
  "age" : "",
  "formation" : "",
  "fossils" : "abundant crinoids",
  "comments" : "IN0222",
  "reference" : "Can't identify a Paynter's Hill,but there is a Paynter's Cemetary 3km SSE of Salem",
  "latLong" : ""
}, {
  "location" : "Salem",
  "county" : "Washington",
  "state" : "Indiana",
  "directions" : "8 km E at Spurgeon Hill 400 meters E of Harristown",
  "age" : "",
  "formation" : "",
  "fossils" : "abundant crinoids",
  "comments" : "IN0223",
  "reference" : "",
  "latLong" : ""
}, {
  "location" : "Salem",
  "county" : "Washington",
  "state" : "Indiana",
  "directions" : "In RR cut just S of Harristown",
  "age" : "Mississippian",
  "formation" : "Salem",
  "fossils" : "abundant fossils - Griffithides,blastoids,etc.",
  "comments" : "IN0224",
  "reference" : "",
  "latLong" : ""
}, {
  "location" : "Salem",
  "county" : "Washington",
  "state" : "Indiana",
  "directions" : "In Salem Limestone. The tan,Mississippian,Salem Limestone is exposed in a railroad cut about 1.6km North of Salem,Washington County. The railroad cut may be (Instructions are a little vague) just East of Indiana 135 and South Harristown[?]",
  "age" : "Mississippian",
  "formation" : "Salem",
  "fossils" : "fossils include mollusks,brachiopods,blastoids,occasional trilobites.",
  "comments" : "IN0225",
  "reference" : "This appears to be a garbled reference to the railroad cut at Harristown 4km E of Salem",
  "latLong" : ""
}, {
  "location" : "Salem",
  "county" : "Washington",
  "state" : "Indiana",
  "directions" : "Indiana,Salem Limestone. The tan Salem Limestone is exposed in a railroad cut about 1.6km North of Salem,Washington County. The railroad cut may be (Instructions are a little vague) just East of Indiana 135 and South of the town of Harristown.",
  "age" : "Mississippian",
  "formation" : "Salem Limestone",
  "fossils" : "Fossils include mollusks,brachiopods,blastoids,occasional trilobites.",
  "comments" : "IN0226",
  "reference" : "",
  "latLong" : ""
}, {
  "location" : "Salem",
  "county" : "Washington",
  "state" : "Indiana",
  "directions" : "NE,in SW1/4NE1/4s5t2nr1e in chert conglomerate",
  "age" : "Mississippian",
  "formation" : "",
  "fossils" : "bryozoa,brachiopods,corals -Lithostrotion",
  "comments" : "IN0227",
  "reference" : "",
  "latLong" : ""
}, {
  "location" : "Salem",
  "county" : "Washington",
  "state" : "Indiana",
  "directions" : "area exposures",
  "age" : "Mississippian",
  "formation" : "St Louis",
  "fossils" : "Numerous Pentremites,Batocrinus,Alloprosallocrinus,Catillocrinus,Bryozoa,Echinoderms,brachiopods,pteropods,gastropods,cephalopods,- Nautilus,Orthoceras,mollusks -Conocardium,arthropods - Leperditia,Phillipsia",
  "comments" : "IN0228",
  "reference" : "",
  "latLong" : ""
}, {
  "location" : "Spergen Hill",
  "county" : "Washington",
  "state" : "Indiana",
  "directions" : "",
  "age" : "",
  "formation" : "",
  "fossils" : "Crinoid -Dorrycrinus",
  "comments" : "IN0229",
  "reference" : "",
  "latLong" : ""
}, {
  "location" : "Spergen Hill",
  "county" : "Washington",
  "state" : "Indiana",
  "directions" : "",
  "age" : "Mississippian",
  "formation" : "Salem",
  "fossils" : "fish teeth-bradyodonts,Cladodus",
  "comments" : "IN0230",
  "reference" : "",
  "latLong" : ""
}, {
  "location" : "Richmond",
  "county" : "Wayne",
  "state" : "Indiana",
  "directions" : "",
  "age" : "",
  "formation" : "",
  "fossils" : "worms-Cornulites",
  "comments" : "IN0231",
  "reference" : "",
  "latLong" : ""
}, {
  "location" : "Richmond",
  "county" : "Wayne",
  "state" : "Indiana",
  "directions" : "",
  "age" : "Ordovician",
  "formation" : "",
  "fossils" : "Brachiopods Dinorthis",
  "comments" : "IN0232",
  "reference" : "",
  "latLong" : ""
}, {
  "location" : "Richmond",
  "county" : "Wayne",
  "state" : "Indiana",
  "directions" : "",
  "age" : "Ordovician",
  "formation" : "Richmond|Whitewater|Elkhorn",
  "fossils" : "?",
  "comments" : "IN0233",
  "reference" : "",
  "latLong" : ""
}, {
  "location" : "Richmond",
  "county" : "Wayne",
  "state" : "Indiana",
  "directions" : "6.2km S. 500 meters W of Founts[?] Road Bridge on Elkhorn Creek",
  "age" : "Ordovician",
  "formation" : "Whitewater",
  "fossils" : "brachiopods,bryozoa",
  "comments" : "IN0234",
  "reference" : "",
  "latLong" : ""
}, {
  "location" : "Richmond",
  "county" : "Wayne",
  "state" : "Indiana",
  "directions" : "6.4km S on Elkhorn Creek between Liberty Pike and IN227",
  "age" : "Ordovician",
  "formation" : "",
  "fossils" : "fossils",
  "comments" : "",
  "reference" : "",
  "latLong" : "https://scholarworks.iu.edu/dspace/bitstream/2022/280/1/C06.pdf"
}, {
  "location" : "Richmond",
  "county" : "Wayne",
  "state" : "Indiana",
  "directions" : "At Thistlewaite Falls in park on NW side of Richmond",
  "age" : "Ordovician",
  "formation" : "",
  "fossils" : "fossils",
  "comments" : "",
  "reference" : "",
  "latLong" : "https://scholarworks.iu.edu/ dspace/bitstream/2022/280/1/C06.pdf"
}, {
  "location" : "Richmond",
  "county" : "Wayne",
  "state" : "Indiana",
  "directions" : "In area exposures between US27 and US35 in NW part of Richmond",
  "age" : "Ordovician",
  "formation" : "",
  "fossils" : "fossils",
  "comments" : "",
  "reference" : "",
  "latLong" : "https://scholarworks.iu.edu/ dspace/bitstream/2022/280/1/C06.pdf"
}, {
  "location" : "Richmond",
  "county" : "Wayne",
  "state" : "Indiana",
  "directions" : "in Roadcuts on US27 1.6km S of Richmond 39d01m40sN 84d30m38sW",
  "age" : "Ordovician",
  "formation" : "Whitewater",
  "fossils" : "Many Cincinnatian outcrops have abundant,well preserved,fossils",
  "comments" : "IN0235",
  "reference" : "Upper Whitewater (shallow subtidal)",
  "latLong" : ""
}, {
  "location" : "Richmond",
  "county" : "Wayne",
  "state" : "Indiana",
  "directions" : "in area roadcuts",
  "age" : "Ordovician",
  "formation" : "Whitewater",
  "fossils" : "abundant fossils",
  "comments" : "IN0236",
  "reference" : "",
  "latLong" : ""
}, {
  "location" : "Bluffton",
  "county" : "Wells",
  "state" : "Indiana",
  "directions" : "N in bioherm in France Stone Co Quarry",
  "age" : "Silurian",
  "formation" : "Liston Creek",
  "fossils" : "reef fossils",
  "comments" : "IN0237",
  "reference" : "",
  "latLong" : ""
}, {
  "location" : "Camden",
  "county" : "White",
  "state" : "Indiana",
  "directions" : "6.5 km SE along Little Deer Creek about 200 meters form North Fork junction",
  "age" : "Silurian",
  "formation" : "Huntington",
  "fossils" : "brachiopods,corals,mollusks,stromatoporoids,trilobites",
  "comments" : "IN0238",
  "reference" : "",
  "latLong" : ""
}, {
  "location" : "Delphi",
  "county" : "White",
  "state" : "Indiana",
  "directions" : "along Golf Links along N old channel of Deer Creek",
  "age" : "",
  "formation" : "",
  "fossils" : "brachiopods,corals,trilobites",
  "comments" : "IN0239",
  "reference" : "",
  "latLong" : ""
}, {
  "location" : "Delphi",
  "county" : "White",
  "state" : "Indiana",
  "directions" : "in area quarries",
  "age" : "",
  "formation" : "",
  "fossils" : "marine fossils",
  "comments" : "IN0240",
  "reference" : "",
  "latLong" : ""
}, {
  "location" : "Delphi",
  "county" : "White",
  "state" : "Indiana",
  "directions" : "to N and NW in quarries",
  "age" : "Silurian",
  "formation" : "",
  "fossils" : "Brachiopods -Conchidium - stromatoporoids,corals - Favosites,Halysites,Heliolites",
  "comments" : "IN0241",
  "reference" : "",
  "latLong" : ""
}, {
  "location" : "Georgetown",
  "county" : "White",
  "state" : "Indiana",
  "directions" : "to S along bluffs of Wabash River to Logansport",
  "age" : "Silurian",
  "formation" : "Huntington Limestone",
  "fossils" : "Brachiopods -Conchidium,Wilsonia[?],Spirifer",
  "comments" : "IN0242",
  "reference" : "'Wilsonia' is a bird - a warbler. Probably a reference to Wilsoniella,a brachiopod",
  "latLong" : ""
}, {
  "location" : "-",
  "county" : "[?]",
  "state" : "Indiana",
  "directions" : "in road cuts near I64 IN37 intersection",
  "age" : "",
  "formation" : "",
  "fossils" : "brachiopods,blastoids,trilobites",
  "comments" : "IN0245",
  "reference" : "",
  "latLong" : ""
}, {
  "location" : "Aurora",
  "county" : "[?]",
  "state" : "Indiana",
  "directions" : "E in roadcut on Interstate",
  "age" : "Mississippian",
  "formation" : "",
  "fossils" : "vertebrates-Ctenacanthus? spine",
  "comments" : "IN0243",
  "reference" : "",
  "latLong" : ""
}, {
  "location" : "Paynter's Hill[?]",
  "county" : "[?]",
  "state" : "Indiana",
  "directions" : "",
  "age" : "Mississippian",
  "formation" : "Warsaw",
  "fossils" : "Shark teeth-Cladodus,Deltodus",
  "comments" : "IN0244",
  "reference" : "Can't identify a Paynter's Hill,but there is a Paynter's Cemetary 3km SSE of Salem",
  "latLong" : ""
} ]