[ {
  "location" : "Au Train Falls",
  "county" : "Alger",
  "state" : "Michigan",
  "directions" : "",
  "age" : "Ordovician",
  "formation" : "Au Train",
  "fossils" : "?",
  "comments" : "MI0001",
  "reference" : "",
  "latLong" : ""
}, {
  "location" : "Miners Castle",
  "county" : "Alger",
  "state" : "Michigan",
  "directions" : "",
  "age" : "Ordovician",
  "formation" : "Au Train",
  "fossils" : "a few cephalopods and gastropods (1 species of each).",
  "comments" : "MI0002",
  "reference" : "",
  "latLong" : ""
}, {
  "location" : "Pictured Rocks",
  "county" : "Alger",
  "state" : "Michigan",
  "directions" : "at top of cliffs",
  "age" : "Ordovician",
  "formation" : "Au Train",
  "fossils" : "?",
  "comments" : "MI0003",
  "reference" : "",
  "latLong" : ""
}, {
  "location" : "Trenary",
  "county" : "Alger",
  "state" : "Michigan",
  "directions" : "S in road and RR cuts",
  "age" : "Ordovician",
  "formation" : "Bony Falls",
  "fossils" : "mollusks,brachiopods,trilobites,ostracods",
  "comments" : "MI0004",
  "reference" : "",
  "latLong" : ""
}, {
  "location" : "Lake Allegan",
  "county" : "Allegan",
  "state" : "Michigan",
  "directions" : "In nodules of yellow",
  "age" : "Mississippian",
  "formation" : "Marshall Sandstone",
  "fossils" : "brachiopods,corals,gastropods",
  "comments" : "MI0005",
  "reference" : "",
  "latLong" : ""
}, {
  "location" : "Alpena",
  "county" : "Alpena",
  "state" : "Michigan",
  "directions" : "",
  "age" : "Devonian",
  "formation" : "",
  "fossils" : "Coral Prismatophyllum",
  "comments" : "MI0006",
  "reference" : "",
  "latLong" : ""
}, {
  "location" : "Alpena",
  "county" : "Alpena",
  "state" : "Michigan",
  "directions" : "6 km S in se1/4s11t30nr8e",
  "age" : "Devonian",
  "formation" : "Thunder Bay",
  "fossils" : "?",
  "comments" : "MI0007",
  "reference" : "",
  "latLong" : ""
}, {
  "location" : "Alpena",
  "county" : "Alpena",
  "state" : "Michigan",
  "directions" : "6.5km upriver near Four Mile Dam on River at Old Potter Farm",
  "age" : "Silurian",
  "formation" : "Thunder Bay",
  "fossils" : "crinoids -Gilbertocrinus,Gennaeocrinus",
  "comments" : "MI0008",
  "reference" : "",
  "latLong" : ""
}, {
  "location" : "Alpena",
  "county" : "Alpena",
  "state" : "Michigan",
  "directions" : "Cemetery in bluff",
  "age" : "Devonian",
  "formation" : "Thunder Bay",
  "fossils" : "rugose coral - Cylindrophyllum",
  "comments" : "MI0009",
  "reference" : "",
  "latLong" : ""
}, {
  "location" : "Alpena",
  "county" : "Alpena",
  "state" : "Michigan",
  "directions" : "In Devonian Dundee Limestone on spoil pits of Martin-Marietta company quarry 2 km E of US523 S of Alpena Rd between Sanford and Godkins Road[?] and SW of Wabash RR tracks.",
  "age" : "Devonian",
  "formation" : "Dundee",
  "fossils" : "?",
  "comments" : "MI0010",
  "reference" : "",
  "latLong" : ""
}, {
  "location" : "Alpena",
  "county" : "Alpena",
  "state" : "Michigan",
  "directions" : "In Devonian Ferron Point Formation in abandoned shale pit of Alpena Portland Cement Co 11.2km N",
  "age" : "Devonian",
  "formation" : "Ferron Point",
  "fossils" : "Edrioasteroids - Krama.",
  "comments" : "MI0011",
  "reference" : "",
  "latLong" : ""
}, {
  "location" : "Alpena",
  "county" : "Alpena",
  "state" : "Michigan",
  "directions" : "In Michigan Alkali Company Quarry",
  "age" : "Devonian",
  "formation" : "Alpena Limestone",
  "fossils" : "Cephalopods - Nephriticerina,Acleistoceras,Alpenoceras",
  "comments" : "MI0012",
  "reference" : "",
  "latLong" : ""
}, {
  "location" : "Alpena",
  "county" : "Alpena",
  "state" : "Michigan",
  "directions" : "In RR cut on E side of town",
  "age" : "Devonian",
  "formation" : "Dock Street Clay",
  "fossils" : "Ostracods",
  "comments" : "MI0013",
  "reference" : "",
  "latLong" : ""
}, {
  "location" : "Alpena",
  "county" : "Alpena",
  "state" : "Michigan",
  "directions" : "In quarry at E end of town s13t31nr8e",
  "age" : "Devonian",
  "formation" : "Genshaw|Newton Creek|Alpena",
  "fossils" : "?",
  "comments" : "MI0014",
  "reference" : "",
  "latLong" : ""
}, {
  "location" : "Alpena",
  "county" : "Alpena",
  "state" : "Michigan",
  "directions" : "In quarry at E end of town se1/4s14t31nr8e",
  "age" : "Devonian",
  "formation" : "Dock Street clay",
  "fossils" : "?",
  "comments" : "MI0015",
  "reference" : "",
  "latLong" : ""
}, {
  "location" : "Alpena",
  "county" : "Alpena",
  "state" : "Michigan",
  "directions" : "In shale pit at Evergreen Cemetery",
  "age" : "Devonian",
  "formation" : "Potter Farm",
  "fossils" : "Ostracods",
  "comments" : "MI0016",
  "reference" : "",
  "latLong" : ""
}, {
  "location" : "Alpena",
  "county" : "Alpena",
  "state" : "Michigan",
  "directions" : "In shale pit at WNW corner of cemetery s21t31nr8e",
  "age" : "Devonian",
  "formation" : "Potter Farm",
  "fossils" : "?",
  "comments" : "MI0017",
  "reference" : "",
  "latLong" : ""
}, {
  "location" : "Alpena",
  "county" : "Alpena",
  "state" : "Michigan",
  "directions" : "NE corner of Evergreen Cemetery",
  "age" : "Devonian",
  "formation" : "Potter Farm",
  "fossils" : "Many fossils - Corals,a few blastoids,Crinoids rare - Megistocrinus,Gennaeocrinus,Synbathocrinus",
  "comments" : "MI0018",
  "reference" : "",
  "latLong" : ""
}, {
  "location" : "Alpena",
  "county" : "Alpena",
  "state" : "Michigan",
  "directions" : "Quarry (abandoned) of Thunder Bay Quarries Co",
  "age" : "Devonian",
  "formation" : "Dock Street Clay",
  "fossils" : "Crinoids. Worked out.",
  "comments" : "MI0019",
  "reference" : "",
  "latLong" : ""
}, {
  "location" : "Alpena",
  "county" : "Alpena",
  "state" : "Michigan",
  "directions" : "in limestone",
  "age" : "Devonian",
  "formation" : "Hamilton",
  "fossils" : "Fish-Ptyctodus",
  "comments" : "MI0020",
  "reference" : "",
  "latLong" : ""
}, {
  "location" : "Bolton",
  "county" : "Alpena",
  "state" : "Michigan",
  "directions" : "2 km NW in RR cut and adjacent fields",
  "age" : "Devonian",
  "formation" : "Alpena Limestone",
  "fossils" : "Ostracods",
  "comments" : "MI0021",
  "reference" : "",
  "latLong" : ""
}, {
  "location" : "El Cajon Bay",
  "county" : "Alpena",
  "state" : "Michigan",
  "directions" : "N of Alpena along Beach and in quarry dumps",
  "age" : "",
  "formation" : "",
  "fossils" : "Pelecypods - Paracyclas",
  "comments" : "MI0022",
  "reference" : "",
  "latLong" : ""
}, {
  "location" : "Ferron Point",
  "county" : "Alpena",
  "state" : "Michigan",
  "directions" : "",
  "age" : "",
  "formation" : "",
  "fossils" : "Stropheodonta,Phacops",
  "comments" : "MI0023",
  "reference" : "",
  "latLong" : ""
}, {
  "location" : "Genshaw",
  "county" : "Alpena",
  "state" : "Michigan",
  "directions" : "13 km NE of Alpena in shale pit in se1/4s18t32N",
  "age" : "Devonian",
  "formation" : "Ferron Point, Upper",
  "fossils" : "Ostracods",
  "comments" : "MI0024",
  "reference" : "",
  "latLong" : ""
}, {
  "location" : "Huron Portland Cement Co Quarry",
  "county" : "Alpena",
  "state" : "Michigan",
  "directions" : "Across Wessel road from Thunder Bay Quarry - Fossils in Genshaw,Newton Creek,Alpena,Dock Street formations",
  "age" : "Devonian",
  "formation" : "Genshaw|Newton Creek|Alpena|Dock Street",
  "fossils" : "?",
  "comments" : "MI0025",
  "reference" : "",
  "latLong" : ""
}, {
  "location" : "Partridge Point",
  "county" : "Alpena",
  "state" : "Michigan",
  "directions" : "Covered by housing - Fossils were collected from Limestone blocks fallen from banks. However,the blocks were washed away by a major storm and homeowners do not allow collecting because of erosion worries.",
  "age" : "Devonian",
  "formation" : "",
  "fossils" : "Crinoids - Dolatocrinus,Megistocrinus,Blastoids,Lipsanocystis",
  "comments" : "MI0026",
  "reference" : "",
  "latLong" : ""
}, {
  "location" : "Rockport",
  "county" : "Alpena",
  "state" : "Michigan",
  "directions" : "",
  "age" : "Devonian",
  "formation" : "",
  "fossils" : "Arthrodire -Protitanichthys; Trepostomata;bryozoa-Fenestrellina",
  "comments" : "MI0027",
  "reference" : "",
  "latLong" : ""
}, {
  "location" : "Rockport",
  "county" : "Alpena",
  "state" : "Michigan",
  "directions" : "3.2km N of Rockport Quarry on beach",
  "age" : "Devonian",
  "formation" : "",
  "fossils" : "Gastropods and cephalopods.",
  "comments" : "MI0028",
  "reference" : "",
  "latLong" : ""
}, {
  "location" : "Rockport",
  "county" : "Alpena",
  "state" : "Michigan",
  "directions" : "In abandoned quarry in s6t32nr9e",
  "age" : "Devonian",
  "formation" : "Bell Shale|Rockport Quarry Limestone|Ferron Point",
  "fossils" : "bryozoa",
  "comments" : "MI0029",
  "reference" : "",
  "latLong" : ""
}, {
  "location" : "Rockport",
  "county" : "Alpena",
  "state" : "Michigan",
  "directions" : "In abandoned quarry of Kelley's Is Lime and Transport Co",
  "age" : "Devonian",
  "formation" : "Rockport Quarry Limestone|Ferron Point",
  "fossils" : "Ostracods",
  "comments" : "MI0030",
  "reference" : "",
  "latLong" : ""
}, {
  "location" : "Rockport",
  "county" : "Alpena",
  "state" : "Michigan",
  "directions" : "Quarry (abandoned) of Kelleys Island Lime and Transport Co - In Upper 2.5m of wall in Ferron Pt Formation shale,clay. At end of Rockport Rd E then N from US23 14 km N of Alpena.",
  "age" : "Devonian",
  "formation" : "",
  "fossils" : "Hexagonaria and many other Fossils -- crinoids,sponges,horn corals,brachiopods,tentaculites,trilobites,gastropods,cephalopods,chelicerates,pelecypods,arthrodire,Dinicthys bones. Lower Rockport Quarry Limestone is not fossiliferous.",
  "comments" : "MI0031",
  "reference" : "",
  "latLong" : ""
}, {
  "location" : "Rockport",
  "county" : "Alpena",
  "state" : "Michigan",
  "directions" : "Quarry (abandoned) of Kelleys Island Lime and Transport Co - greenish Bell shale in drainage ditch at NE end of quarry",
  "age" : "Devonian",
  "formation" : "",
  "fossils" : "small exposure Small crinoid heads weathering out.",
  "comments" : "MI0032",
  "reference" : "",
  "latLong" : ""
}, {
  "location" : "Sulphur Island",
  "county" : "Alpena",
  "state" : "Michigan",
  "directions" : "Thunder Bay",
  "age" : "Devonian",
  "formation" : "",
  "fossils" : "black petrified wood in waters around island",
  "comments" : "MI0033",
  "reference" : "",
  "latLong" : ""
}, {
  "location" : "Thunder Bay River",
  "county" : "Alpena",
  "state" : "Michigan",
  "directions" : "At Seven Point Dam (dam removed and exposure flooded by Norway Point Dam)",
  "age" : "Devonian",
  "formation" : "",
  "fossils" : "Fossils",
  "comments" : "MI0034",
  "reference" : "",
  "latLong" : ""
}, {
  "location" : "Thunder Bay River",
  "county" : "Alpena",
  "state" : "Michigan",
  "directions" : "Below Norway Point Dam (Six Mile Dam,Seven Mile Dam) in bed and banks of River",
  "age" : "Devonian",
  "formation" : "Norway Point",
  "fossils" : "Spinocyrtia,Ostracods",
  "comments" : "MI0035",
  "reference" : "",
  "latLong" : ""
}, {
  "location" : "Thunder Bay River",
  "county" : "Alpena",
  "state" : "Michigan",
  "directions" : "Broadwell's Sawmill on Thunder Bay river - classic Four Mile Dam Formation site worked by Rominger and Grabau - now submerged",
  "age" : "Devonian",
  "formation" : "",
  "fossils" : "?",
  "comments" : "MI0036",
  "reference" : "",
  "latLong" : ""
}, {
  "location" : "Thunder Bay River",
  "county" : "Alpena",
  "state" : "Michigan",
  "directions" : "Four Mile Dam on Thunder Bay River - regional exposures",
  "age" : "Devonian",
  "formation" : "",
  "fossils" : "?",
  "comments" : "MI0037",
  "reference" : "",
  "latLong" : ""
}, {
  "location" : "Thunder Bay River",
  "county" : "Alpena",
  "state" : "Michigan",
  "directions" : "In Shale exposure on S bank 2 km downstream from Four Mile Dam (Also known as Fletcher Dam,Three Mile Dam,Broadwell's Saw Mill)",
  "age" : "Devonian",
  "formation" : "Norway Point",
  "fossils" : "Ostracods.",
  "comments" : "MI0038",
  "reference" : "",
  "latLong" : ""
}, {
  "location" : "Thunder Bay River",
  "county" : "Alpena",
  "state" : "Michigan",
  "directions" : "sites submerged by dam",
  "age" : "",
  "formation" : "",
  "fossils" : "?",
  "comments" : "MI0039",
  "reference" : "",
  "latLong" : ""
}, {
  "location" : "Coldwater",
  "county" : "Branch",
  "state" : "Michigan",
  "directions" : "area shale exposures",
  "age" : "",
  "formation" : "",
  "fossils" : "Mooreoceras",
  "comments" : "MI0040",
  "reference" : "",
  "latLong" : ""
}, {
  "location" : "Coldwater",
  "county" : "Branch",
  "state" : "Michigan",
  "directions" : "at old Wolverine Portland Cement Co quarry",
  "age" : "Mississippian",
  "formation" : "Coldwater",
  "fossils" : "Mooreoceras",
  "comments" : "MI0041",
  "reference" : "",
  "latLong" : ""
}, {
  "location" : "Union",
  "county" : "Branch",
  "state" : "Michigan",
  "directions" : "",
  "age" : "Mississippian",
  "formation" : "Coldwater Shale",
  "fossils" : "?",
  "comments" : "MI0042",
  "reference" : "",
  "latLong" : ""
}, {
  "location" : "Union City",
  "county" : "Branch",
  "state" : "Michigan",
  "directions" : "area exposures",
  "age" : "Mississippian",
  "formation" : "Coldwater",
  "fossils" : "Cephalopods - Mooreoceras (pyrite)",
  "comments" : "MI0043",
  "reference" : "",
  "latLong" : ""
}, {
  "location" : "Albion",
  "county" : "Calhoun",
  "state" : "Michigan",
  "directions" : "N in quarry",
  "age" : "Pennsylvanian",
  "formation" : "Parma Sandstone",
  "fossils" : "plants - Calamites",
  "comments" : "MI0044",
  "reference" : "",
  "latLong" : ""
}, {
  "location" : "Albion",
  "county" : "Calhoun",
  "state" : "Michigan",
  "directions" : "NE in area road cuts",
  "age" : "Pennsylvanian",
  "formation" : "Parma Sandstone",
  "fossils" : "plants - Calamites",
  "comments" : "MI0045",
  "reference" : "",
  "latLong" : ""
}, {
  "location" : "Battle Creek",
  "county" : "Calhoun",
  "state" : "Michigan",
  "directions" : "area exposures",
  "age" : "Mississippian",
  "formation" : "Marshall",
  "fossils" : "?",
  "comments" : "MI0046",
  "reference" : "",
  "latLong" : ""
}, {
  "location" : "Deveraux",
  "county" : "Calhoun",
  "state" : "Michigan",
  "directions" : "S in RR Cut in s6t2sr3w2",
  "age" : "Pennsylvanian",
  "formation" : "Parma Sandstone",
  "fossils" : "plants - Calamites",
  "comments" : "MI0047",
  "reference" : "",
  "latLong" : ""
}, {
  "location" : "Marshall",
  "county" : "Calhoun",
  "state" : "Michigan",
  "directions" : "area exposures",
  "age" : "Mississippian",
  "formation" : "Marshall",
  "fossils" : "pelecypods,cephalopods,ostracods,gastropods,brachiopods,a few trilobites",
  "comments" : "MI0048",
  "reference" : "",
  "latLong" : ""
}, {
  "location" : "Marshall",
  "county" : "Calhoun",
  "state" : "Michigan",
  "directions" : "in quarry",
  "age" : "Mississippian",
  "formation" : "Marshall sandstone",
  "fossils" : "Mooreoceras",
  "comments" : "MI0049",
  "reference" : "",
  "latLong" : ""
}, {
  "location" : "Beaver Island",
  "county" : "Charlevoix",
  "state" : "Michigan",
  "directions" : "1 km NE of CG station on shore",
  "age" : "Devonian",
  "formation" : "Bois Blanc Limestone",
  "fossils" : "pelecypods",
  "comments" : "MI0050",
  "reference" : "",
  "latLong" : ""
}, {
  "location" : "Charlevoix",
  "county" : "Charlevoix",
  "state" : "Michigan",
  "directions" : "1 km W in abandoned quarry",
  "age" : "Devonian",
  "formation" : "Gravel Point",
  "fossils" : "corals",
  "comments" : "MI0051",
  "reference" : "",
  "latLong" : ""
}, {
  "location" : "Charlevoix",
  "county" : "Charlevoix",
  "state" : "Michigan",
  "directions" : "3 km W IN,in ledges and bluffs along Lake Michigan shore (Type locality for Gravel Point Formation)",
  "age" : "Devonian",
  "formation" : "Gravel Point",
  "fossils" : "corals",
  "comments" : "MI0052",
  "reference" : "",
  "latLong" : ""
}, {
  "location" : "Charlevoix",
  "county" : "Charlevoix",
  "state" : "Michigan",
  "directions" : "Area Quarries",
  "age" : "Devonian",
  "formation" : "Ferron Point, Upper",
  "fossils" : "Ostracods",
  "comments" : "MI0053",
  "reference" : "",
  "latLong" : ""
}, {
  "location" : "Norwood",
  "county" : "Charlevoix",
  "state" : "Michigan",
  "directions" : "2 km N along Lake Michigan shore at very low water",
  "age" : "Devonian",
  "formation" : "Petoskey",
  "fossils" : "Ostracods",
  "comments" : "MI0054",
  "reference" : "",
  "latLong" : ""
}, {
  "location" : "Norwood",
  "county" : "Charlevoix",
  "state" : "Michigan",
  "directions" : "2 km N on old road",
  "age" : "Devonian",
  "formation" : "Petoskey",
  "fossils" : "Atrypa,Ostracods",
  "comments" : "MI0055",
  "reference" : "",
  "latLong" : ""
}, {
  "location" : "Norwood",
  "county" : "Charlevoix",
  "state" : "Michigan",
  "directions" : "2-3 km N in ledges along Lake Michigan",
  "age" : "Devonian",
  "formation" : "Petoskey",
  "fossils" : "corals",
  "comments" : "MI0056",
  "reference" : "",
  "latLong" : ""
}, {
  "location" : "Trout Island",
  "county" : "Charlevoix",
  "state" : "Michigan",
  "directions" : "S and W side of SE point of island",
  "age" : "Devonian",
  "formation" : "Bois Blanc Limestone",
  "fossils" : "trilobites",
  "comments" : "MI0057",
  "reference" : "",
  "latLong" : ""
}, {
  "location" : "-",
  "county" : "Charlevoix,Emmet",
  "state" : "Michigan",
  "directions" : "In Middle Devonian Charlevoix Limestone-Petoskey,Gravel Point,Whiskey Creek,Norwood,Ellsworth formations.",
  "age" : "Devonian",
  "formation" : "",
  "fossils" : "Corals Hexagonaria,Aulacophyllum,Heliophyllum,Aulopora,Favosites,Syringopora,Trachypora. Brachiopods - Athyris,Cyrtina,Leptaena,Mucrospirifer,Productella,Rhipidomella,Spinocyrtia. Mollusks Euomphalus,Pleurotomaria,Tentaculites. Aviculopecten",
  "comments" : "MI0058",
  "reference" : "",
  "latLong" : ""
}, {
  "location" : "Afton",
  "county" : "Cheboygan",
  "state" : "Michigan",
  "directions" : "1 km W 4 km S along highway and in schoolyard",
  "age" : "",
  "formation" : "",
  "fossils" : "corals",
  "comments" : "MI0059",
  "reference" : "",
  "latLong" : ""
}, {
  "location" : "Afton",
  "county" : "Cheboygan",
  "state" : "Michigan",
  "directions" : "In abandoned Campbell stone Co quarry",
  "age" : "",
  "formation" : "",
  "fossils" : "coral - Favosites",
  "comments" : "MI0060",
  "reference" : "",
  "latLong" : ""
}, {
  "location" : "Burt Lake",
  "county" : "Cheboygan",
  "state" : "Michigan",
  "directions" : "along lake shore",
  "age" : "Devonian",
  "formation" : "",
  "fossils" : "corals,Gastropods-Platyceras,cephalopods,trilobites",
  "comments" : "MI0061",
  "reference" : "",
  "latLong" : ""
}, {
  "location" : "Cordell",
  "county" : "Chippewa",
  "state" : "Michigan",
  "directions" : "2 km SE in abandoned quarry of Scott Quarry Co",
  "age" : "Silurian",
  "formation" : "Cordell",
  "fossils" : "brachiopods,corals",
  "comments" : "MI0062",
  "reference" : "",
  "latLong" : ""
}, {
  "location" : "Drummond Island",
  "county" : "Chippewa",
  "state" : "Michigan",
  "directions" : "",
  "age" : "Ordovician",
  "formation" : "Richmond",
  "fossils" : "abundant fossils",
  "comments" : "MI0069",
  "reference" : "",
  "latLong" : ""
}, {
  "location" : "Drummond Island",
  "county" : "Chippewa",
  "state" : "Michigan",
  "directions" : "",
  "age" : "Silurian",
  "formation" : "",
  "fossils" : "brachiopods -Pentameroides,coral - Favosites,Syringopora",
  "comments" : "MI0063",
  "reference" : "",
  "latLong" : ""
}, {
  "location" : "Drummond Island",
  "county" : "Chippewa",
  "state" : "Michigan",
  "directions" : "5 km NNE of Poe Pt",
  "age" : "Ordovician",
  "formation" : "Black River Limestone",
  "fossils" : "corals,crinoids,bryozoa,brachiopods,trilobites",
  "comments" : "MI0064",
  "reference" : "",
  "latLong" : ""
}, {
  "location" : "Drummond Island",
  "county" : "Chippewa",
  "state" : "Michigan",
  "directions" : "At Chippewa Pt",
  "age" : "Ordovician",
  "formation" : "Richmond",
  "fossils" : "abundant fossils",
  "comments" : "MI0065",
  "reference" : "",
  "latLong" : ""
}, {
  "location" : "Drummond Island",
  "county" : "Chippewa",
  "state" : "Michigan",
  "directions" : "area exposure especially along North Shore of island",
  "age" : "",
  "formation" : "",
  "fossils" : "abundant fossils",
  "comments" : "MI0066",
  "reference" : "",
  "latLong" : ""
}, {
  "location" : "Lime Island",
  "county" : "Chippewa",
  "state" : "Michigan",
  "directions" : "along shore of St Marys River",
  "age" : "Silurian",
  "formation" : "Lime Island Dolomite",
  "fossils" : "corals and brachiopod molds",
  "comments" : "MI0067",
  "reference" : "",
  "latLong" : ""
}, {
  "location" : "Raber",
  "county" : "Chippewa",
  "state" : "Michigan",
  "directions" : "3 km SE along old logging road",
  "age" : "Silurian",
  "formation" : "Schoolcraft|Cordell",
  "fossils" : "Abundant corals stromatoporoids,brachiopods,cephalopods",
  "comments" : "MI0068",
  "reference" : "",
  "latLong" : ""
}, {
  "location" : "Sault Pt",
  "county" : "Chippewa",
  "state" : "Michigan",
  "directions" : "on South shore of Whitefish Bay",
  "age" : "Ordovician",
  "formation" : "Au Train",
  "fossils" : "gastropods (1 genus)",
  "comments" : "MI0070",
  "reference" : "",
  "latLong" : ""
}, {
  "location" : "Sault St Marie",
  "county" : "Chippewa",
  "state" : "Michigan",
  "directions" : "S at West Neebish Channel in material blasted from channel",
  "age" : "Ordovician",
  "formation" : "Trenton",
  "fossils" : "diverse fossils -trilobites,cephalopods. Scyphozoa,brachiopods,bryozoa,corals",
  "comments" : "MI0071",
  "reference" : "",
  "latLong" : ""
}, {
  "location" : "Scotts Quarry",
  "county" : "Chippewa",
  "state" : "Michigan",
  "directions" : "s29t44nr4w",
  "age" : "Silurian",
  "formation" : "Manistique",
  "fossils" : "Actinoceras,Huroniella,Huronia",
  "comments" : "MI0072",
  "reference" : "",
  "latLong" : ""
}, {
  "location" : "St Johns",
  "county" : "Clinton",
  "state" : "Michigan",
  "directions" : "NE in pit on E side of Scott Rd",
  "age" : "",
  "formation" : "",
  "fossils" : "fossils",
  "comments" : "MI0073",
  "reference" : "",
  "latLong" : ""
}, {
  "location" : "-",
  "county" : "Delta",
  "state" : "Michigan",
  "directions" : "In s12t41nr21w,s7t41nr20w",
  "age" : "Ordovician",
  "formation" : "Bills Creek",
  "fossils" : "1 graptolite,1 echinoderm,3 bryozoa,5 brachiopods,3 trilobites,3 ostracods",
  "comments" : "MI0106",
  "reference" : "",
  "latLong" : ""
}, {
  "location" : "Bark River",
  "county" : "Delta",
  "state" : "Michigan",
  "directions" : "3 km N",
  "age" : "Ordovician",
  "formation" : "Chandler Falls?",
  "fossils" : "gastropods",
  "comments" : "MI0074",
  "reference" : "",
  "latLong" : ""
}, {
  "location" : "Bay de Noc",
  "county" : "Delta",
  "state" : "Michigan",
  "directions" : "",
  "age" : "",
  "formation" : "",
  "fossils" : "corals - Streptelasma,Columnaria",
  "comments" : "MI0075",
  "reference" : "",
  "latLong" : ""
}, {
  "location" : "Bay de Noc",
  "county" : "Delta",
  "state" : "Michigan",
  "directions" : "on E side at Burnt Bluff 15 km SW of Garden Village",
  "age" : "Silurian",
  "formation" : "Manistique",
  "fossils" : "Hendricks--Byron dolomites -- a few brachiopods,corals,stromatoporoids,ostracods",
  "comments" : "MI0076",
  "reference" : "",
  "latLong" : ""
}, {
  "location" : "Bay de Noc",
  "county" : "Delta",
  "state" : "Michigan",
  "directions" : "on E side at Burnt Bluff 15 km SW of Garden Village",
  "age" : "Silurian",
  "formation" : "Manistique|Hendricks|Byron dolomites",
  "fossils" : "a few brachiopods,corals,stromatoporoids,ostracods",
  "comments" : "MI0077",
  "reference" : "",
  "latLong" : ""
}, {
  "location" : "Bony Falls",
  "county" : "Delta",
  "state" : "Michigan",
  "directions" : "On Escanaba River in T41nr24w",
  "age" : "Ordovician",
  "formation" : "Bony Falls",
  "fossils" : "Gastropods,corals,brachiopods,trilobites,pelecypod,cephalopods,ostracods",
  "comments" : "MI0078",
  "reference" : "",
  "latLong" : ""
}, {
  "location" : "Bony Falls",
  "county" : "Delta",
  "state" : "Michigan",
  "directions" : "S1t41nr24w in Limestone near hydroelectric power plant on Escanaba River",
  "age" : "Ordovician",
  "formation" : "",
  "fossils" : "Maclurites,Endoceras to 1 meters,fucoids,Strophomena,Stromatocerium,crinoid fragments,Eoleperditia,Ctenodonta,Orthis,Pterygometopus,Foerstephyllum",
  "comments" : "MI0079",
  "reference" : "",
  "latLong" : ""
}, {
  "location" : "Bony Falls",
  "county" : "Delta",
  "state" : "Michigan",
  "directions" : "on Escanaba River in T41nr24w",
  "age" : "Ordovician",
  "formation" : "Bony Falls",
  "fossils" : "Gastropods,corals,brachiopods,trilobites,pelecypod,cephalopods,ostracods",
  "comments" : "MI0080",
  "reference" : "",
  "latLong" : ""
}, {
  "location" : "Chandler Falls",
  "county" : "Delta",
  "state" : "Michigan",
  "directions" : "5 km N of Escanaba t39nr22wt",
  "age" : "Ordovician",
  "formation" : "Chandler Falls",
  "fossils" : "Gastropods,brachiopods,trilobites,pelecypod,crinoids,bryozoa,corals,sponges,plants",
  "comments" : "MI0081",
  "reference" : "",
  "latLong" : ""
}, {
  "location" : "Cornell",
  "county" : "Delta",
  "state" : "Michigan",
  "directions" : "12 km SW",
  "age" : "Ordovician",
  "formation" : "Groos Quarry",
  "fossils" : "Gastropods,brachiopods,trilobites,pelecypod,crinoids,bryozoa",
  "comments" : "MI0082",
  "reference" : "",
  "latLong" : ""
}, {
  "location" : "Cornell",
  "county" : "Delta",
  "state" : "Michigan",
  "directions" : "2.2 km E on Escanaba River",
  "age" : "Ordovician",
  "formation" : "Trenton",
  "fossils" : "Gastropods,brachiopods",
  "comments" : "MI0083",
  "reference" : "",
  "latLong" : ""
}, {
  "location" : "Cornell",
  "county" : "Delta",
  "state" : "Michigan",
  "directions" : "400 meters N of concrete bridge over Escanaba River",
  "age" : "Ordovician",
  "formation" : "Trenton",
  "fossils" : "48 species - Phycodes,Streptelasma,Prasopora,Cornulites,Catazyga,Cyclospira,Plesiomys[?],Leptaena,Hesperorthis,Sowerbyella,Platystrophia,Rafinesquina,Rhynchotrema,Strophomena",
  "comments" : "MI0084",
  "reference" : "No citations for 'Plesiomys' or anything remotely similar (apparently a brachiopod?) 050603",
  "latLong" : ""
}, {
  "location" : "Escanaba",
  "county" : "Delta",
  "state" : "Michigan",
  "directions" : "5 km N at Chandler Falls along Escanaba River in Limestone and shale bluffs",
  "age" : "Ordovician",
  "formation" : "",
  "fossils" : "54 species of invertebrates",
  "comments" : "MI0085",
  "reference" : "",
  "latLong" : ""
}, {
  "location" : "Escanaba",
  "county" : "Delta",
  "state" : "Michigan",
  "directions" : "5 km N at Chandler Falls along Escanaba River in Limestone outcrop",
  "age" : "Ordovician",
  "formation" : "Trenton",
  "fossils" : "Pleurocystites,Edrioaster",
  "comments" : "MI0086",
  "reference" : "",
  "latLong" : ""
}, {
  "location" : "Escanaba",
  "county" : "Delta",
  "state" : "Michigan",
  "directions" : "8 km N s1t39nr23w at Groos Quarry",
  "age" : "Ordovician",
  "formation" : "Groos Quarry",
  "fossils" : "Gastropods,brachiopods,trilobites,pelecypod,crinoids,bryozoa",
  "comments" : "MI0087",
  "reference" : "",
  "latLong" : ""
}, {
  "location" : "Escanaba",
  "county" : "Delta",
  "state" : "Michigan",
  "directions" : "8 km N s1t39nr23w at Groos Quarry then 400 meters NW on island in Escanaba River",
  "age" : "Ordovician",
  "formation" : "Groos Quarry",
  "fossils" : "Pelecypods,brachiopods",
  "comments" : "MI0088",
  "reference" : "",
  "latLong" : ""
}, {
  "location" : "Fayette State Park",
  "county" : "Delta",
  "state" : "Michigan",
  "directions" : "",
  "age" : "Silurian",
  "formation" : "Hendricks",
  "fossils" : "Conodonts, Microvertebrates-fish scales-Loganellia,Valyalepis,Zuegelepis",
  "comments" : "MI0209",
  "reference" : "",
  "latLong" : "http://findarticles.com/p/articles/mi_qa3790/is_199907/ai_n8855647"
}, {
  "location" : "Ford River",
  "county" : "Delta",
  "state" : "Michigan",
  "directions" : "In bed of river in s5t38nr23w",
  "age" : "Ordovician",
  "formation" : "Groos Quarry",
  "fossils" : "a few brachiopods,Scyphozoa",
  "comments" : "MI0089",
  "reference" : "",
  "latLong" : ""
}, {
  "location" : "Groos",
  "county" : "Delta",
  "state" : "Michigan",
  "directions" : "8 km N of Escanaba at Richler Quarry",
  "age" : "Ordovician",
  "formation" : "",
  "fossils" : "26 species,Whitella",
  "comments" : "MI0090",
  "reference" : "Presumably one of the several quarries around the mouth of Richler Creek near 45.8029N,87.0953W",
  "latLong" : ""
}, {
  "location" : "Groos",
  "county" : "Delta",
  "state" : "Michigan",
  "directions" : "At paper mill in limestones at small island in the Escanaba River",
  "age" : "",
  "formation" : "",
  "fossils" : "Whitella",
  "comments" : "MI0091",
  "reference" : "",
  "latLong" : ""
}, {
  "location" : "Haymeadow Creek",
  "county" : "Delta",
  "state" : "Michigan",
  "directions" : "along Haymeadow Creek nw1/4s19t42nr20w",
  "age" : "Ordovician",
  "formation" : "Haymeadow Creek",
  "fossils" : "fossils",
  "comments" : "MI0092",
  "reference" : "",
  "latLong" : ""
}, {
  "location" : "Haymeadow Creek",
  "county" : "Delta",
  "state" : "Michigan",
  "directions" : "s19t42nr20w",
  "age" : "Ordovician",
  "formation" : "Bills Creek",
  "fossils" : "Bills Creek faunas",
  "comments" : "MI0093",
  "reference" : "",
  "latLong" : ""
}, {
  "location" : "Haymeadow Creek",
  "county" : "Delta",
  "state" : "Michigan",
  "directions" : "s2,s19t42nr40w",
  "age" : "Silurian",
  "formation" : "Bills Creek",
  "fossils" : "abundant Lingula,Clidophorus,Dalmanella",
  "comments" : "MI0094",
  "reference" : "",
  "latLong" : ""
}, {
  "location" : "Hinkin's Hill[?]",
  "county" : "Delta",
  "state" : "Michigan",
  "directions" : "N for 5 km along road",
  "age" : "Ordovician",
  "formation" : "Richmond",
  "fossils" : "corals,stromatoporoids,Calapoecia,Halysites,Columnaria,Beatricea",
  "comments" : "MI0095",
  "reference" : "Original says Silurian. Can't identify a 'Hinkin's Hill' in Delta County",
  "latLong" : ""
}, {
  "location" : "Isabella",
  "county" : "Delta",
  "state" : "Michigan",
  "directions" : "2.5 km W in roadside ditch SE corner of s35t41nr19w",
  "age" : "Silurian",
  "formation" : "Moss Lake",
  "fossils" : "a few poor brachiopods and crinoid columnals",
  "comments" : "MI0096",
  "reference" : "",
  "latLong" : ""
}, {
  "location" : "Little Bay de Noc",
  "county" : "Delta",
  "state" : "Michigan",
  "directions" : "In area road cuts",
  "age" : "Silurian",
  "formation" : "Bills Creek",
  "fossils" : "graptolites,Leptobolus",
  "comments" : "MI0097",
  "reference" : "",
  "latLong" : ""
}, {
  "location" : "Little Bay de Noc",
  "county" : "Delta",
  "state" : "Michigan",
  "directions" : "In road cut in nw1/4s24t39nr22w",
  "age" : "Ordovician",
  "formation" : "Stonington",
  "fossils" : "abundant fossils",
  "comments" : "MI0098",
  "reference" : "",
  "latLong" : ""
}, {
  "location" : "Little Bay de Noc",
  "county" : "Delta",
  "state" : "Michigan",
  "directions" : "along E shore",
  "age" : "Silurian",
  "formation" : "Bills Creek",
  "fossils" : "graptolites,Leptobolus",
  "comments" : "MI0099",
  "reference" : "",
  "latLong" : ""
}, {
  "location" : "Little Bay de Noc",
  "county" : "Delta",
  "state" : "Michigan",
  "directions" : "along South shore in se1/4s26t39nr22w",
  "age" : "Ordovician",
  "formation" : "Stonington",
  "fossils" : "abundant fossils",
  "comments" : "MI0100",
  "reference" : "",
  "latLong" : ""
}, {
  "location" : "Little Bay de Noc",
  "county" : "Delta",
  "state" : "Michigan",
  "directions" : "along shore in s14t39nr22w+s23t39nr22w",
  "age" : "Ordovician",
  "formation" : "Bills Creek|Stonington",
  "fossils" : "abundant fossils",
  "comments" : "MI0101",
  "reference" : "",
  "latLong" : ""
}, {
  "location" : "Manistique",
  "county" : "Delta",
  "state" : "Michigan",
  "directions" : "35 km SW 13 km NE of Pt Detour in Limestone",
  "age" : "Silurian",
  "formation" : "",
  "fossils" : "Discosorus",
  "comments" : "MI0102",
  "reference" : "",
  "latLong" : ""
}, {
  "location" : "Perkins",
  "county" : "Delta",
  "state" : "Michigan",
  "directions" : "500 meters W in s5t41nr22w",
  "age" : "Ordovician",
  "formation" : "Groos Quarry",
  "fossils" : "crinoid plates,other Groos Quarry fossils",
  "comments" : "MI0103",
  "reference" : "",
  "latLong" : ""
}, {
  "location" : "Rapid River",
  "county" : "Delta",
  "state" : "Michigan",
  "directions" : "E in bed of Rapid River",
  "age" : "Ordovician",
  "formation" : "Trenton",
  "fossils" : "Mollusks,brachiopods,trilobites,bryozoa",
  "comments" : "MI0104",
  "reference" : "",
  "latLong" : ""
}, {
  "location" : "Stonington Peninsula",
  "county" : "Delta",
  "state" : "Michigan",
  "directions" : "",
  "age" : "",
  "formation" : "",
  "fossils" : "brachiopods",
  "comments" : "MI0105",
  "reference" : "",
  "latLong" : ""
}, {
  "location" : "Breen Mine",
  "county" : "Dickinson",
  "state" : "Michigan",
  "directions" : "S22T39NR28W at top of mine in ledges",
  "age" : "Cambrian",
  "formation" : "Munising",
  "fossils" : "Trilobite fragments",
  "comments" : "MI0107",
  "reference" : "",
  "latLong" : ""
}, {
  "location" : "Iron Mountain",
  "county" : "Dickinson",
  "state" : "Michigan",
  "directions" : "North side of Pewabic Mine",
  "age" : "Cambrian",
  "formation" : "Munising",
  "fossils" : "Trilobites,phosphatic brachiopods",
  "comments" : "MI0108",
  "reference" : "",
  "latLong" : ""
}, {
  "location" : "Waucedah",
  "county" : "Dickinson",
  "state" : "Michigan",
  "directions" : "1 km N in ledges on N side of US2",
  "age" : "Cambrian",
  "formation" : "Munising",
  "fossils" : "Trilobites,phosphatic brachiopods",
  "comments" : "MI0109",
  "reference" : "",
  "latLong" : ""
}, {
  "location" : "Grand Ledge",
  "county" : "Eaton",
  "state" : "Michigan",
  "directions" : "2 km N Pennsylvanian plants in clay quarry.",
  "age" : "Pennsylvanian",
  "formation" : "",
  "fossils" : "Calamites,Sigillaria,Alethopteris,Sphenopteris,Cordaites,Annularia,Neuropteris,Asterophyllites,Codaianthus[?],Cardiocarpon",
  "comments" : "MI0110",
  "reference" : "No citations for 'Codaianthus' or some plausible misspellings 050603",
  "latLong" : ""
}, {
  "location" : "Grand Ledge",
  "county" : "Eaton",
  "state" : "Michigan",
  "directions" : "In Pennsylvanian shales in area exposures",
  "age" : "Pennsylvanian",
  "formation" : "",
  "fossils" : "plants",
  "comments" : "MI0111",
  "reference" : "",
  "latLong" : ""
}, {
  "location" : "Grand Ledge",
  "county" : "Eaton",
  "state" : "Michigan",
  "directions" : "In area outcrops",
  "age" : "Pennsylvanian",
  "formation" : "Saginaw",
  "fossils" : "many plants,brachiopods,gastropods,cephalopods,a few trilobites and ostracods,a few fish.",
  "comments" : "MI0112",
  "reference" : "",
  "latLong" : ""
}, {
  "location" : "Grand Ledge",
  "county" : "Eaton",
  "state" : "Michigan",
  "directions" : "In outcrops and quarries along Grand River.",
  "age" : "Pennsylvanian",
  "formation" : "Saginaw",
  "fossils" : "many plants,brachiopods,gastropods,cephalopods,a few trilobites and ostracods,a few fish.",
  "comments" : "MI0113",
  "reference" : "",
  "latLong" : ""
}, {
  "location" : "Grand Ledge",
  "county" : "Eaton",
  "state" : "Michigan",
  "directions" : "In pits in NW1/4t4Nr52 area outcrops",
  "age" : "Pennsylvanian",
  "formation" : "Saginaw",
  "fossils" : "many plants,brachiopods,gastropods,cephalopods,a few trilobites and ostracods,a few fish.",
  "comments" : "MI0114",
  "reference" : "",
  "latLong" : ""
}, {
  "location" : "Bay Shore",
  "county" : "Emmet",
  "state" : "Michigan",
  "directions" : "In abandoned quarries and extending into Charlevoix County",
  "age" : "Devonian",
  "formation" : "Charlevoix|Petoskey",
  "fossils" : "corals",
  "comments" : "MI0115",
  "reference" : "",
  "latLong" : ""
}, {
  "location" : "Bay View",
  "county" : "Emmet",
  "state" : "Michigan",
  "directions" : "2 km E in Kegomic quarry on S shore of Mud Lake just E of Harbor Springs Rd",
  "age" : "",
  "formation" : "",
  "fossils" : "Gypidula,Corals",
  "comments" : "MI0116",
  "reference" : "",
  "latLong" : ""
}, {
  "location" : "Bay View",
  "county" : "Emmet",
  "state" : "Michigan",
  "directions" : "2 km W in quarry on S shore of Mud Lake on US31 just E of Harbor Springs Rd",
  "age" : "Devonian",
  "formation" : "Petoskey",
  "fossils" : "Ostracods",
  "comments" : "MI0117",
  "reference" : "",
  "latLong" : ""
}, {
  "location" : "Bay View",
  "county" : "Emmet",
  "state" : "Michigan",
  "directions" : "In ledges on Little traverse Bay at Pennsylvania RR station above Blue Shale",
  "age" : "Devonian",
  "formation" : "Gravel Point",
  "fossils" : "corals",
  "comments" : "MI0118",
  "reference" : "",
  "latLong" : ""
}, {
  "location" : "Bay View",
  "county" : "Emmet",
  "state" : "Michigan",
  "directions" : "On Little Traverse Bay near old Pennsylvania RR depot at junction of Development Ave and MI31",
  "age" : "Devonian",
  "formation" : "Gravel Point",
  "fossils" : "Ostracods",
  "comments" : "MI0119",
  "reference" : "",
  "latLong" : ""
}, {
  "location" : "Bay View",
  "county" : "Emmet",
  "state" : "Michigan",
  "directions" : "On S shore of Mud Lake on MI131 about 1 km N of termination se1/4sw1/4s27t35nr5w",
  "age" : "Devonian",
  "formation" : "Petoskey",
  "fossils" : "Gypidula",
  "comments" : "MI0120",
  "reference" : "",
  "latLong" : ""
}, {
  "location" : "Bear Creek",
  "county" : "Emmet",
  "state" : "Michigan",
  "directions" : "In Buff Limestone at Little Traverse Bay",
  "age" : "",
  "formation" : "",
  "fossils" : "corals - Cylindrophyllum",
  "comments" : "MI0121",
  "reference" : "",
  "latLong" : ""
}, {
  "location" : "Petoskey",
  "county" : "Emmet",
  "state" : "Michigan",
  "directions" : "3 km W in sw1/4s2 + se1/4s3t34nr6w",
  "age" : "Devonian",
  "formation" : "Gravel Point",
  "fossils" : "fossils",
  "comments" : "MI0122",
  "reference" : "",
  "latLong" : ""
}, {
  "location" : "Petoskey",
  "county" : "Emmet",
  "state" : "Michigan",
  "directions" : "4 km NE in quarry ne1/4nw1/4s34t35nr5w about 400 meters SE of crossing of Pere Marquette RR W of US31",
  "age" : "",
  "formation" : "",
  "fossils" : "Gypidula,Hexagonaria",
  "comments" : "MI0123",
  "reference" : "",
  "latLong" : ""
}, {
  "location" : "Petoskey",
  "county" : "Emmet",
  "state" : "Michigan",
  "directions" : "Abandoned Northern Lime Co quarry on Little Traverse Bay on Eastern part of Petoskey",
  "age" : "Devonian",
  "formation" : "",
  "fossils" : "?",
  "comments" : "MI0124",
  "reference" : "",
  "latLong" : ""
}, {
  "location" : "Petoskey",
  "county" : "Emmet",
  "state" : "Michigan",
  "directions" : "Abandoned Superior Quarry of Northern Lime Co near Nine Mile Point",
  "age" : "Devonian",
  "formation" : "",
  "fossils" : "?",
  "comments" : "MI0125",
  "reference" : "",
  "latLong" : ""
}, {
  "location" : "Petoskey",
  "county" : "Emmet",
  "state" : "Michigan",
  "directions" : "Along Lake Michigan shore from Charlevoix to Petoskey at Little Traverse Bay",
  "age" : "Devonian",
  "formation" : "",
  "fossils" : "?",
  "comments" : "MI0126",
  "reference" : "",
  "latLong" : ""
}, {
  "location" : "Petoskey",
  "county" : "Emmet",
  "state" : "Michigan",
  "directions" : "In Portland Cement Company Quarry 3 km W of Petoskey in",
  "age" : "Devonian",
  "formation" : "Gravel Point",
  "fossils" : "40 species of corals,brachiopods - Spinocyrtia,pelecypods,nautiloids,a few trilobites.",
  "comments" : "MI0127",
  "reference" : "",
  "latLong" : ""
}, {
  "location" : "Petoskey",
  "county" : "Emmet",
  "state" : "Michigan",
  "directions" : "In area beach gravels",
  "age" : "",
  "formation" : "",
  "fossils" : "Corals (Petoskey stones)",
  "comments" : "MI0128",
  "reference" : "",
  "latLong" : ""
}, {
  "location" : "Petoskey",
  "county" : "Emmet",
  "state" : "Michigan",
  "directions" : "In quarry on Little Traverse Bay s32t35nr5w",
  "age" : "Devonian",
  "formation" : "Charlevoix",
  "fossils" : "?",
  "comments" : "MI0129",
  "reference" : "",
  "latLong" : ""
}, {
  "location" : "Petoskey",
  "county" : "Emmet",
  "state" : "Michigan",
  "directions" : "Kegonic[?] Quarry between US31 and MI131 1.6km E of --Bay View between Pickerel Rd and Penn RR",
  "age" : "Devonian",
  "formation" : "",
  "fossils" : "?",
  "comments" : "MI0130",
  "reference" : "Can't identify a Kegonic Quarry near Petoskey. There are a number of quarries. Very likely,many contain fossils.",
  "latLong" : ""
}, {
  "location" : "Hillsdale",
  "county" : "Hillsdale",
  "state" : "Michigan",
  "directions" : "In Germain's[?] quarry",
  "age" : "",
  "formation" : "",
  "fossils" : "Mooreoceras",
  "comments" : "MI0131",
  "reference" : "",
  "latLong" : ""
}, {
  "location" : "Moscow",
  "county" : "Hillsdale",
  "state" : "Michigan",
  "directions" : "In nw1/4 nw1/4 s4 Jefferson Township",
  "age" : "Mississippian",
  "formation" : "Marshall",
  "fossils" : "?",
  "comments" : "MI0132",
  "reference" : "",
  "latLong" : ""
}, {
  "location" : "Moscow",
  "county" : "Hillsdale",
  "state" : "Michigan",
  "directions" : "In sw1/4 sw1/4 s26 Allen Township",
  "age" : "Mississippian",
  "formation" : "Marshall",
  "fossils" : "?",
  "comments" : "MI0133",
  "reference" : "",
  "latLong" : ""
}, {
  "location" : "Bay Port",
  "county" : "Huron",
  "state" : "Michigan",
  "directions" : "In J O Burroughs and Son Quarry.",
  "age" : "Mississippian",
  "formation" : "",
  "fossils" : "fossils",
  "comments" : "MI0134",
  "reference" : "",
  "latLong" : ""
}, {
  "location" : "Flat Rock Pt",
  "county" : "Huron",
  "state" : "Michigan",
  "directions" : "2 km SW at Hardwood Pt",
  "age" : "Mississippian",
  "formation" : "Marshall Sandstone",
  "fossils" : "Mooreoceras",
  "comments" : "MI0135",
  "reference" : "",
  "latLong" : ""
}, {
  "location" : "Grindstone City",
  "county" : "Huron",
  "state" : "Michigan",
  "directions" : "In grindstone quarries",
  "age" : "Mississippian",
  "formation" : "Marshall",
  "fossils" : "?",
  "comments" : "MI0136",
  "reference" : "",
  "latLong" : ""
}, {
  "location" : "Pointe Aux Barques",
  "county" : "Huron",
  "state" : "Michigan",
  "directions" : "In grindstone quarries",
  "age" : "Mississippian",
  "formation" : "Marshall",
  "fossils" : "?",
  "comments" : "MI0137",
  "reference" : "",
  "latLong" : ""
}, {
  "location" : "Pointe Aux Barques",
  "county" : "Huron",
  "state" : "Michigan",
  "directions" : "near lighthouse",
  "age" : "Mississippian",
  "formation" : "Coldwater",
  "fossils" : "cephalopods",
  "comments" : "MI0138",
  "reference" : "",
  "latLong" : ""
}, {
  "location" : "Au Gres River",
  "county" : "Iosco",
  "state" : "Michigan",
  "directions" : "",
  "age" : "Mississippian",
  "formation" : "Marshall Sandstone",
  "fossils" : "Allorisma,Imitoceras",
  "comments" : "MI0139",
  "reference" : "",
  "latLong" : ""
}, {
  "location" : "Au Gres River",
  "county" : "Iosco",
  "state" : "Michigan",
  "directions" : "In limestones",
  "age" : "Mississippian",
  "formation" : "",
  "fossils" : "pelecypods",
  "comments" : "MI0140",
  "reference" : "",
  "latLong" : ""
}, {
  "location" : "Columbia",
  "county" : "Jackson",
  "state" : "Michigan",
  "directions" : "area exposures",
  "age" : "Mississippian",
  "formation" : "Marshall",
  "fossils" : "?",
  "comments" : "MI0141",
  "reference" : "",
  "latLong" : ""
}, {
  "location" : "Hanover",
  "county" : "Jackson",
  "state" : "Michigan",
  "directions" : "In quarry 4 km SW in quarry in ne1/4s31t4sr2w",
  "age" : "Mississippian",
  "formation" : "Marshall",
  "fossils" : "clams,crinoids,nautiloids,ammonoids,ostracods",
  "comments" : "MI0142",
  "reference" : "",
  "latLong" : ""
}, {
  "location" : "Jackson",
  "county" : "Jackson",
  "state" : "Michigan",
  "directions" : "8 km S along US127 in glacial esker, 1200 meters E in gravel pit",
  "age" : "Mississippian",
  "formation" : "Marshall",
  "fossils" : "pelecypods,cephalopods,ostracods,gastropods,brachiopods,a few trilobites",
  "comments" : "MI0143",
  "reference" : "",
  "latLong" : ""
}, {
  "location" : "Jackson",
  "county" : "Jackson",
  "state" : "Michigan",
  "directions" : "8 km S in road cut and gravel pit W of junction of Meyers and Wetherby Roads",
  "age" : "Mississippian",
  "formation" : "Marshall",
  "fossils" : "pelecypods,cephalopods,ostracods,gastropods,brachiopods,a few trilobites",
  "comments" : "MI0144",
  "reference" : "",
  "latLong" : ""
}, {
  "location" : "Jackson",
  "county" : "Jackson",
  "state" : "Michigan",
  "directions" : "along hwy between Lansing and Jackson 500 meters S of Bentley Corners",
  "age" : "Pennsylvanian",
  "formation" : "Parma Sandstone",
  "fossils" : "plants - Calamites",
  "comments" : "MI0145",
  "reference" : "",
  "latLong" : ""
}, {
  "location" : "Jackson",
  "county" : "Jackson",
  "state" : "Michigan",
  "directions" : "area exposures and shale pits",
  "age" : "Pennsylvanian",
  "formation" : "",
  "fossils" : "Plants -- Calamites",
  "comments" : "MI0146",
  "reference" : "",
  "latLong" : ""
}, {
  "location" : "Napoleon",
  "county" : "Jackson",
  "state" : "Michigan",
  "directions" : "In RR cut 5 km N",
  "age" : "Mississippian",
  "formation" : "Marshall",
  "fossils" : "?",
  "comments" : "MI0147",
  "reference" : "",
  "latLong" : ""
}, {
  "location" : "Parma",
  "county" : "Jackson",
  "state" : "Michigan",
  "directions" : "NE in quarry in nw1/4s29t2sr2w",
  "age" : "Pennsylvanian",
  "formation" : "Parma Sandstone",
  "fossils" : "plants - Calamites",
  "comments" : "MI0148",
  "reference" : "",
  "latLong" : ""
}, {
  "location" : "Parma",
  "county" : "Jackson",
  "state" : "Michigan",
  "directions" : "NNE along road in s27t2sr2w",
  "age" : "Pennsylvanian",
  "formation" : "Parma Sandstone",
  "fossils" : "plants - Calamites",
  "comments" : "MI0149",
  "reference" : "",
  "latLong" : ""
}, {
  "location" : "Parma",
  "county" : "Jackson",
  "state" : "Michigan",
  "directions" : "Poorly preserved Pennsylvanian Fossils in Parma Formation.",
  "age" : "Pennsylvanian",
  "formation" : "Parma",
  "fossils" : "?",
  "comments" : "MI0150",
  "reference" : "",
  "latLong" : ""
}, {
  "location" : "Rives Junction",
  "county" : "Jackson",
  "state" : "Michigan",
  "directions" : "area exposures and shale pits Pennsylvanian Plants",
  "age" : "Pennsylvanian",
  "formation" : "",
  "fossils" : "Calamites",
  "comments" : "MI0151",
  "reference" : "",
  "latLong" : ""
}, {
  "location" : "North Fox Island",
  "county" : "Leelanau",
  "state" : "Michigan",
  "directions" : "",
  "age" : "Devonian",
  "formation" : "Bois Blanc Limestone",
  "fossils" : "Pelecypods",
  "comments" : "MI0152",
  "reference" : "",
  "latLong" : ""
}, {
  "location" : "Manistique Lake",
  "county" : "Luce",
  "state" : "Michigan",
  "directions" : "2 km N 150 meters N of hwy 98",
  "age" : "Silurian",
  "formation" : "Manitoulin dolomite",
  "fossils" : "a few corals,brachiopods,trilobites",
  "comments" : "MI0153",
  "reference" : "",
  "latLong" : ""
}, {
  "location" : "Newberry",
  "county" : "Luce",
  "state" : "Michigan",
  "directions" : "In material in gravel pits",
  "age" : "Ordovician",
  "formation" : "Collingwood",
  "fossils" : "3 trilobites,3 graptolites,4 brachiopods,1 cephalopod",
  "comments" : "MI0154",
  "reference" : "",
  "latLong" : ""
}, {
  "location" : "Allenville",
  "county" : "Mackinac",
  "state" : "Michigan",
  "directions" : "1.2 km S in rock pile of Mackinac Breccia",
  "age" : "Devonian",
  "formation" : "Bois Blanc Limestone",
  "fossils" : "pelecypods",
  "comments" : "MI0155",
  "reference" : "",
  "latLong" : ""
}, {
  "location" : "Big St Martin Is (in Lake Huron)",
  "county" : "Mackinac",
  "state" : "Michigan",
  "directions" : "along shore in Mackinac breccia",
  "age" : "Devonian",
  "formation" : "Bois Blanc Limestone",
  "fossils" : "pelecypods",
  "comments" : "MI0156",
  "reference" : "",
  "latLong" : ""
}, {
  "location" : "Gould City",
  "county" : "Mackinac",
  "state" : "Michigan",
  "directions" : "1 km S in rock piles along fences",
  "age" : "Silurian",
  "formation" : "",
  "fossils" : "Ormoceras",
  "comments" : "MI0157",
  "reference" : "",
  "latLong" : ""
}, {
  "location" : "Hendrick's Quarry",
  "county" : "Mackinac",
  "state" : "Michigan",
  "directions" : "",
  "age" : "Silurian",
  "formation" : "Burnt Bluff",
  "fossils" : "Ormoceras,Discosorus,Stokesoceras",
  "comments" : "MI0158",
  "reference" : "",
  "latLong" : ""
}, {
  "location" : "Hendrick's Quarry",
  "county" : "Mackinac",
  "state" : "Michigan",
  "directions" : "In nw1/4s6t44nr8w and ne1/4s1t44nr9w",
  "age" : "Silurian",
  "formation" : "Hendricks dolomite",
  "fossils" : "ostracods,corals,brachiopods,trilobites",
  "comments" : "MI0159",
  "reference" : "",
  "latLong" : ""
}, {
  "location" : "Hunt's Spur",
  "county" : "Mackinac",
  "state" : "Michigan",
  "directions" : "1 km N sw1/4s7t42nr12w",
  "age" : "Silurian",
  "formation" : "Manistique",
  "fossils" : "Actinoceras",
  "comments" : "MI0160",
  "reference" : "",
  "latLong" : ""
}, {
  "location" : "Raber",
  "county" : "Mackinac",
  "state" : "Michigan",
  "directions" : "In area quarries",
  "age" : "",
  "formation" : "",
  "fossils" : "silicified corals",
  "comments" : "MI0161",
  "reference" : "",
  "latLong" : ""
}, {
  "location" : "St Ignace",
  "county" : "Mackinac",
  "state" : "Michigan",
  "directions" : "2 km NE in cliff on N side of Cheesman Rd",
  "age" : "Devonian",
  "formation" : "",
  "fossils" : "pelecypods",
  "comments" : "MI0162",
  "reference" : "",
  "latLong" : ""
}, {
  "location" : "Austin Mine #2",
  "county" : "Marquette",
  "state" : "Michigan",
  "directions" : "ne1/4ne1/4sw1/4s20t48nr25w",
  "age" : "Ordovician",
  "formation" : "Au Train",
  "fossils" : "a few cephalopods (1 species)",
  "comments" : "MI0163",
  "reference" : "",
  "latLong" : ""
}, {
  "location" : "Ishpeming",
  "county" : "Marquette",
  "state" : "Michigan",
  "directions" : "In area mines material used for cutting and polished",
  "age" : "",
  "formation" : "",
  "fossils" : "Silicified stromatolites",
  "comments" : "MI0164",
  "reference" : "",
  "latLong" : ""
}, {
  "location" : "Ishpeming",
  "county" : "Marquette",
  "state" : "Michigan",
  "directions" : "at Empire Mine",
  "age" : "Proterozoic",
  "formation" : "Negaunee",
  "fossils" : "Grypania",
  "comments" : "MI0165",
  "reference" : "",
  "latLong" : ""
}, {
  "location" : "Marquette",
  "county" : "Marquette",
  "state" : "Michigan",
  "directions" : "In area mines material used for cutting and polished",
  "age" : "",
  "formation" : "",
  "fossils" : "Silicified stromatolites",
  "comments" : "MI0166",
  "reference" : "",
  "latLong" : ""
}, {
  "location" : "Marquette",
  "county" : "Marquette",
  "state" : "Michigan",
  "directions" : "Upper Peninsula",
  "age" : "Proterozoic",
  "formation" : "",
  "fossils" : "stromatolites",
  "comments" : "MI0167",
  "reference" : "",
  "latLong" : ""
}, {
  "location" : "Negaunee",
  "county" : "Marquette",
  "state" : "Michigan",
  "directions" : "In area mines material used for cutting and polished",
  "age" : "",
  "formation" : "",
  "fossils" : "Silicified stromatolites",
  "comments" : "MI0168",
  "reference" : "",
  "latLong" : ""
}, {
  "location" : "Republic",
  "county" : "Marquette",
  "state" : "Michigan",
  "directions" : "In area mines material used for cutting and polished",
  "age" : "",
  "formation" : "",
  "fossils" : "Silicified stromatolites",
  "comments" : "MI0169",
  "reference" : "",
  "latLong" : ""
}, {
  "location" : "Harris",
  "county" : "Menominee",
  "state" : "Michigan",
  "directions" : "1 km E in roadside exposure in s12t38nr25w",
  "age" : "Ordovician",
  "formation" : "Trenton",
  "fossils" : "pelecypods",
  "comments" : "MI0170",
  "reference" : "",
  "latLong" : ""
}, {
  "location" : "Spalding",
  "county" : "Menominee",
  "state" : "Michigan",
  "directions" : "1.2 km NW",
  "age" : "Ordovician",
  "formation" : "Bony Falls",
  "fossils" : "Brachiopods,cephalopods",
  "comments" : "MI0171",
  "reference" : "",
  "latLong" : ""
}, {
  "location" : "Spalding",
  "county" : "Menominee",
  "state" : "Michigan",
  "directions" : "500 meters NW on US2",
  "age" : "Ordovician",
  "formation" : "Bony Falls",
  "fossils" : "Brachiopods",
  "comments" : "MI0172",
  "reference" : "",
  "latLong" : ""
}, {
  "location" : "Wilson",
  "county" : "Menominee",
  "state" : "Michigan",
  "directions" : "3 km ESE",
  "age" : "Ordovician",
  "formation" : "Chandler Falls, Upper",
  "fossils" : "a few brachiopods and gastropods",
  "comments" : "MI0173",
  "reference" : "",
  "latLong" : ""
}, {
  "location" : "-",
  "county" : "Monroe",
  "state" : "Michigan",
  "directions" : "In dolomite outcrops. Generally unfossiliferous,but some horizons fossiliferous",
  "age" : "Paleozoic",
  "formation" : "Monroe",
  "fossils" : "brachiopods - Spirifer,Meristella,Nucleospira,gastropods,a few crinoids,corals,bryozoa. Very rarely mollusks.",
  "comments" : "MI0181",
  "reference" : "",
  "latLong" : ""
}, {
  "location" : "Bedford Township",
  "county" : "Monroe",
  "state" : "Michigan",
  "directions" : "at Little Sink and Little Lake in area quarries",
  "age" : "Paleozoic",
  "formation" : "Monroe",
  "fossils" : "Retzia",
  "comments" : "MI0174",
  "reference" : "",
  "latLong" : ""
}, {
  "location" : "Dundee Quarry",
  "county" : "Monroe",
  "state" : "Michigan",
  "directions" : "In Limestone",
  "age" : "",
  "formation" : "",
  "fossils" : "Atrypa,Spirifer,Orthis,Stropheodonta,Paracyclas,Conocardium,Pleuronotus,Phacops,Proetus,Dalmanites,Stromatopora,Zaphrentis,Heliophyllum,Favosites",
  "comments" : "MI0175",
  "reference" : "",
  "latLong" : ""
}, {
  "location" : "Macon Quarry",
  "county" : "Monroe",
  "state" : "Michigan",
  "directions" : "in Limestone",
  "age" : "",
  "formation" : "",
  "fossils" : "Atrypa,Spirifer,Orthis,Stropheodonta,Paracyclas,Conocardium,Pleuronotus,Phacops,Proetus,Dalmanites,Stromatopora,Stictopora,Zaphrentis,Heliophyllum,Favosites",
  "comments" : "MI0176",
  "reference" : "",
  "latLong" : ""
}, {
  "location" : "Maybee",
  "county" : "Monroe",
  "state" : "Michigan",
  "directions" : "Crystalline Sulfur and Sylvania sandstone with internal gastropod and brachiopod molds. Quarry now closed.",
  "age" : "Devonian",
  "formation" : "",
  "fossils" : "?",
  "comments" : "MI0177",
  "reference" : "",
  "latLong" : ""
}, {
  "location" : "Ottawa Lake",
  "county" : "Monroe",
  "state" : "Michigan",
  "directions" : "In old Daniels Quarry at head of Lake",
  "age" : "",
  "formation" : "",
  "fossils" : "Pterinea",
  "comments" : "MI0178",
  "reference" : "",
  "latLong" : ""
}, {
  "location" : "Petersburg",
  "county" : "Monroe",
  "state" : "Michigan",
  "directions" : "10 km SSE in abandoned Cummins Quarry",
  "age" : "Devonian",
  "formation" : "Detroit River",
  "fossils" : "pelecypods",
  "comments" : "MI0179",
  "reference" : "",
  "latLong" : ""
}, {
  "location" : "Plum Creek",
  "county" : "Monroe",
  "state" : "Michigan",
  "directions" : "In dolomite quarries",
  "age" : "",
  "formation" : "",
  "fossils" : "Goniophora",
  "comments" : "MI0180",
  "reference" : "",
  "latLong" : ""
}, {
  "location" : "Pontiac",
  "county" : "Oakland",
  "state" : "Michigan",
  "directions" : "In Pennsylvanian La Salle Formation",
  "age" : "",
  "formation" : "",
  "fossils" : "Crinoids - Erisocrinus,Caucacrocrinus,Clathocrinus",
  "comments" : "MI0182",
  "reference" : "",
  "latLong" : ""
}, {
  "location" : "Holland",
  "county" : "Ottawa",
  "state" : "Michigan",
  "directions" : "",
  "age" : "Mississippian",
  "formation" : "Marshall",
  "fossils" : "?",
  "comments" : "MI0183",
  "reference" : "",
  "latLong" : ""
}, {
  "location" : "Black Lake",
  "county" : "Presque Isle",
  "state" : "Michigan",
  "directions" : "In quarry on shore",
  "age" : "Devonian",
  "formation" : "Ferron Point",
  "fossils" : "Ostracods",
  "comments" : "MI0184",
  "reference" : "",
  "latLong" : ""
}, {
  "location" : "Calcite",
  "county" : "Presque Isle",
  "state" : "Michigan",
  "directions" : "In area quarries in 10 sections i.e. SE part of t35nr5e",
  "age" : "Devonian",
  "formation" : "Dundee",
  "fossils" : "fossil corals",
  "comments" : "MI0185",
  "reference" : "",
  "latLong" : ""
}, {
  "location" : "Calcite",
  "county" : "Presque Isle",
  "state" : "Michigan",
  "directions" : "In dump pile of Michigan Limestone Co Quarry",
  "age" : "Devonian",
  "formation" : "Bell Shale",
  "fossils" : "Ostracods",
  "comments" : "MI0186",
  "reference" : "",
  "latLong" : ""
}, {
  "location" : "Liske",
  "county" : "Presque Isle",
  "state" : "Michigan",
  "directions" : "6.3 km E in road cut on US23",
  "age" : "Devonian",
  "formation" : "Rockport Quarry",
  "fossils" : "black corals",
  "comments" : "MI0187",
  "reference" : "",
  "latLong" : ""
}, {
  "location" : "Long Lake",
  "county" : "Presque Isle",
  "state" : "Michigan",
  "directions" : "adjacent to county road on W shore 800 meters N of county line",
  "age" : "Devonian",
  "formation" : "Genshaw",
  "fossils" : "Cyrtina,Ostracods",
  "comments" : "MI0188",
  "reference" : "",
  "latLong" : ""
}, {
  "location" : "Rogers City",
  "county" : "Presque Isle",
  "state" : "Michigan",
  "directions" : "",
  "age" : "Devonian",
  "formation" : "Dundee",
  "fossils" : "corals",
  "comments" : "MI0189",
  "reference" : "",
  "latLong" : ""
}, {
  "location" : "Rogers City",
  "county" : "Presque Isle",
  "state" : "Michigan",
  "directions" : "16 km SE on US23 W of Trout Creek s15t34nr6e",
  "age" : "Devonian",
  "formation" : "Rockport Quarry",
  "fossils" : "Ostracods",
  "comments" : "MI0190",
  "reference" : "",
  "latLong" : ""
}, {
  "location" : "Rogers City",
  "county" : "Presque Isle",
  "state" : "Michigan",
  "directions" : "In US steel company Limestone quarry",
  "age" : "Devonian",
  "formation" : "Traverse Group",
  "fossils" : "Wide variety of fossils especially from Bell shale outcrops.",
  "comments" : "MI0191",
  "reference" : "",
  "latLong" : ""
}, {
  "location" : "Rogers city",
  "county" : "Presque Isle",
  "state" : "Michigan",
  "directions" : "14 km S in road cut on US23",
  "age" : "",
  "formation" : "",
  "fossils" : "coral -Favosites",
  "comments" : "MI0192",
  "reference" : "",
  "latLong" : ""
}, {
  "location" : "Rogers city",
  "county" : "Presque Isle",
  "state" : "Michigan",
  "directions" : "area exposures",
  "age" : "",
  "formation" : "",
  "fossils" : "Longstaffia",
  "comments" : "MI0193",
  "reference" : "",
  "latLong" : ""
}, {
  "location" : "Saginaw valley",
  "county" : "Saginaw",
  "state" : "Michigan",
  "directions" : "In dumps of old coal mines in area",
  "age" : "Pennsylvanian",
  "formation" : "Saginaw",
  "fossils" : "many plants,brachiopods,gastropods,cephalopods,a few trilobites and ostracods,a few fish.",
  "comments" : "MI0194",
  "reference" : "",
  "latLong" : ""
}, {
  "location" : "Manistique",
  "county" : "Schoolcraft",
  "state" : "Michigan",
  "directions" : "8 km NNW in road cut and abandoned quarry on hwy 94",
  "age" : "Silurian",
  "formation" : "Hendricks dolomite",
  "fossils" : "corals,brachiopods,stromatoporoids,crinoid columns",
  "comments" : "MI0195",
  "reference" : "",
  "latLong" : ""
}, {
  "location" : "Manistique",
  "county" : "Schoolcraft",
  "state" : "Michigan",
  "directions" : "In abandoned quarry",
  "age" : "Silurian",
  "formation" : "Cordell|Schoolcraft dolomite",
  "fossils" : "corals,brachiopods,ostracods,bryozoa,mollusks",
  "comments" : "MI0196",
  "reference" : "",
  "latLong" : ""
}, {
  "location" : "Whitedale",
  "county" : "Schoolcraft",
  "state" : "Michigan",
  "directions" : "In area quarries",
  "age" : "",
  "formation" : "",
  "fossils" : "silicified coral",
  "comments" : "MI0197",
  "reference" : "",
  "latLong" : ""
}, {
  "location" : "Milan",
  "county" : "Washtenaw",
  "state" : "Michigan",
  "directions" : "",
  "age" : "Devonian",
  "formation" : "Silica Shale",
  "fossils" : "Phyllocarids - Pseudodontichthys; Arthrodire fish plates -Protitanichthys,Paleoniscoid fish bones - Kentuckia?",
  "comments" : "MI0198",
  "reference" : "",
  "latLong" : ""
}, {
  "location" : "Rockwood",
  "county" : "Wayne",
  "state" : "Michigan",
  "directions" : "SE in Michigan Silica Co pit",
  "age" : "Devonian",
  "formation" : "Sylvania",
  "fossils" : "pelecypods",
  "comments" : "MI0199",
  "reference" : "",
  "latLong" : ""
}, {
  "location" : "Sibley",
  "county" : "Wayne",
  "state" : "Michigan",
  "directions" : "3 km N of Trenton in Quarry",
  "age" : "Devonian",
  "formation" : "Dundee|Lucas",
  "fossils" : "corals - brachiopods",
  "comments" : "MI0200",
  "reference" : "This would probably be the Sibley Quarry at 42.1640N,83.1835W. The orginal included a reference to the Anderson fomration, but I can't find a citationf for a Devonian Anderson formation in the Michigan Basin",
  "latLong" : ""
}, {
  "location" : "Sibley",
  "county" : "Wayne",
  "state" : "Michigan",
  "directions" : "3 km N of Trenton in Quarry",
  "age" : "Devonian",
  "formation" : "Dundee|Lucas",
  "fossils" : "corals - brachiopods",
  "comments" : "MI0201",
  "reference" : "",
  "latLong" : ""
}, {
  "location" : "Sibley",
  "county" : "Wayne",
  "state" : "Michigan",
  "directions" : "In abandoned quarry of Solvay Process Company",
  "age" : "Devonian",
  "formation" : "",
  "fossils" : "Trilobite - Proetus; Coral - Hexagonaria;Brachiopods",
  "comments" : "MI0202",
  "reference" : "This would probably be the Sibley Quarry at 42.1640N,83.1835W",
  "latLong" : ""
}, {
  "location" : "Trenton",
  "county" : "Wayne",
  "state" : "Michigan",
  "directions" : "3 km N at Sibley quarry of Solvay Process Co",
  "age" : "Devonian",
  "formation" : "Detroit River",
  "fossils" : "pelecypods",
  "comments" : "MI0203",
  "reference" : "",
  "latLong" : ""
}, {
  "location" : "Big Hill[?] (Homkion[?] Hill)",
  "county" : "[?]",
  "state" : "Michigan",
  "directions" : "In s11t39nr22w",
  "age" : "Ordovician",
  "formation" : "Big Hill",
  "fossils" : "abundant fossils,mostly corals (9 taxa) and bryozoa",
  "comments" : "MI0204",
  "reference" : "",
  "latLong" : ""
}, {
  "location" : "Michigan",
  "county" : "[?]",
  "state" : "Michigan",
  "directions" : "At least three,perhaps five sets of whale bones from scattered locations. Several have been dated and seem anomalously young - a few hundred or few thousand years. May be trade artifacts rather than fossils.",
  "age" : "Pleistocene",
  "formation" : "",
  "fossils" : "whale bones",
  "comments" : "MI0205",
  "reference" : "",
  "latLong" : ""
}, {
  "location" : "NW Michigan",
  "county" : "[?]",
  "state" : "Michigan",
  "directions" : "Lake shores near Petoskey,Atwood,Norwood,MI,silicified fossil corals ('Hexagonaria'-Billingsastrea) known as Petoskey stones from the Devonian Onondaga equivalent,the Bois Blanc Formation.",
  "age" : "Devonian",
  "formation" : "",
  "fossils" : "corals",
  "comments" : "MI0206",
  "reference" : "",
  "latLong" : ""
}, {
  "location" : "Northern Peninsula",
  "county" : "[?]",
  "state" : "Michigan",
  "directions" : "",
  "age" : "Silurian",
  "formation" : "",
  "fossils" : "coral - Halysites",
  "comments" : "MI0207",
  "reference" : "",
  "latLong" : ""
}, {
  "location" : "Southern Michigan",
  "county" : "[?]",
  "state" : "Michigan",
  "directions" : "Fossils in Pleistocene glacial deposits.",
  "age" : "Pleistocene",
  "formation" : "",
  "fossils" : "A variety of Ordovician,Silurian,Devonian and Mississippian fossils -- often water worn.",
  "comments" : "MI0208",
  "reference" : "",
  "latLong" : ""
} ]